Workbook

Sheet Summary
C3: Current Assumptions | G3: Exit Upside
B5: Ticker | C5: Current Date | D5: Share Price | E5: 2025E EV / EBITDA | F5: 2026E EV / EBITDA | G5: Exit Date | H5: EV / EBITDA | I5: Share Price | J5: IRR | K5: MOIC
B6: BABA | C6: 45917 | D6: 166 | E6: =BABA!C29 -> 12.815645 | F6: =BABA!C30 -> 11.06475 | G6: 47848 | H6: 15 | I6: =BABA!C42 -> 413.12504 | J6: =BABA!C48 -> 0.18808465 | K6: =BABA!C47 -> 2.488705
B7: AMZN | C7: =C9 -> 45917 | D7: 234.05 | E7: =AMZN!F8 -> 15.406567 | F7: =AMZN!F9 -> 12.882062 | G7: 47848 | H7: 15 | I7: =AMZN!F19 -> 605.83516 | J7: =AMZN!F24 -> 0.19694565 | K7: =AMZN!F23 -> 2.5884861
B8: FOUR | C8: 46113 | D8: 42.56 | E8: =FOUR!F8 -> 8.3126804 | F8: =FOUR!F9 -> 6.7758824 | G8: 47848 | H8: 10 | I8: =FOUR!F19 -> 284.07553 | J8: =FOUR!F24 -> 0.49086949 | K8: =FOUR!F23 -> 6.674707
B9: WBD | C9: =C6 -> 45917 | D9: 18 | E9: =WBD!C8 -> 8.9869441 | F9: =WBD!C9 -> 8.7111679 | G9: 47848 | H9: 10 | I9: =WBD!C18 -> 36.513268 | J9: =WBD!C23 -> 0.14304467 | K9: =WBD!C22 -> 2.0285149
B10: XPOF | C10: =C8 -> 46113 | D10: 8.41 | E10: =XPOF!F8 -> 6.2264071 | F10: =XPOF!F9 -> 5.7866372 | G10: 47848 | H10: 8 | I10: =XPOF!F19 -> 30.297391 | J10: =XPOF!F24 -> 0.30947276 | K10: =XPOF!F23 -> 3.6025435
B11: ST | C11: =ST!A2 -> 46113 | D11: =ST!F3 -> 32.45 | E11: =ST!F9 -> 8.3720656 | F11: =ST!F10 -> 8.0061281 | G11: =ST!A12 -> 47848 | H11: =ST!F14 -> 10 | I11: =ST!F20 -> 101.70669 | J11: =ST!F25 -> 0.27166928 | K11: =ST!F24 -> 3.1342584
B12: RDDT | C12: =C11 -> 46113 | D12: 131.84 | E12: =RDDT!F65 -> 20.788132 | F12: =RDDT!F66 -> 13.810375 | G12: 48213 | H12: 18 | I12: =RDDT!F76 -> 453.74602 | J12: =RDDT!F82 -> 0.23951154 | K12: =RDDT!F81 -> 3.4416415

Sheet BABA
B1: FX | C1: 0.14
B2: (RMB, FYE March) | C2: FY2022A | D2: FY2023A | E2: FY2024A | F2: FY2025A
B3: Revenue
B4: TTG (Taobao & Tmall Group) | C4: 591.58 | D4: 582.731 | E4: 434.893 | F4: 449.827
B5: Cloud Intelligence Group | C5: 74.568 | D5: 77.203 | E5: 106.374 | F5: 118.028
B6: AIDC (International Commerce) | C6: 61.078 | D6: 69.204 | E6: 102.598 | F6: 132.3
B7: Cainiao (Smart Logistics) | C7: 46.107 | D7: 55.681 | E7: 99.02 | F7: 101.272
B8: Local Services | C8: 44.616 | D8: 50.112 | E8: 59.802 | F8: 67.076
B9: All Others | C9: =C10-SUM(C4:C8) -> 35.113 | D9: =D10-SUM(D4:D8) -> 33.756 | E9: =E10-SUM(E4:E8) -> 138.481 | F9: =F10-SUM(F4:F8) -> 127.844
B10: Consolidated Total | C10: 853.062 | D10: 868.687 | E10: 941.168 | F10: 996.347
B12: EBITA
B13: TTG (Taobao & Tmall Group) | C13: 182.431 | D13: 184.862 | E13: 194.827 | F13: 196.232
B14: Cloud Intelligence Group | C14: 1.146 | D14: 1.422 | E14: 6.121 | F14: 10.556
B15: AIDC (International Commerce) | C15: -8.991 | D15: -5.62 | E15: -8.035 | F15: -15.137
B16: Cainiao (Smart Logistics) | C16: -1.465 | D16: -0.391 | E16: 1.402 | F16: 0.302
B17: Local Services | C17: -22.092 | D17: -14.021 | E17: -9.812 | F17: -3.689
B18: All Others | C18: =C19-SUM(C13:C17) -> #VALUE! | D18: =D19-SUM(D13:D17) -> -18.341 | E18: =E19-SUM(E13:E17) -> -19.475 | F18: =F19-SUM(F13:F17) -> -15.199
B19: Consolidated Total | C19: =SUM(C13:C18) -> #VALUE! | D19: 147.911 | E19: 165.028 | F19: 173.065
A21: =Summary!C6 -> 45917 | B21: Current Capitalization
B22: Current Share Price | C22: =Summary!D6 -> 166
B23: Shares Outstanding | C23: 2270.6467
B24: Market Cap | C24: =C22*C23 -> 376927.36
B25: (+) Debt | C25: 34625.2
B26: (-) Cash | C26: -59742
B27: (+) Minority Interest | C27: 11199
B28: TEV | C28: =SUM(C24:C27) -> 363009.56
B29: 2025E EV / EBITDA | C29: =C28/(F86*1000) -> 12.815645
B30: 2026E EV / EBITDA | C30: =C28/(G86*1000) -> 11.06475
A32: =Summary!G6 -> 47848 | B32: Exit Upside
B33: FY2030E EBITDA | C33: =K86*1000 -> 52900.066
B34: Multiple | C34: =Summary!H6 -> 15
B35: TEV | C35: =C33*C34 -> 793500.99
B36: (-) Current Debt | C36: =-C25 -> -34625.2
B37: (+) Current Cash | C37: =-C26 -> 59742
B38: (-) Current Minority Interest | C38: =-C27 -> -11199
B39: (+) Cumulative Levered FCF | C39: =C57 -> 130642.22
B40: Market Cap | C40: =SUM(C35:C39) -> 938061.02
B41: Current Shares Outstanding | C41: =C23 -> 2270.6467
A42: =A32 -> 47848 | B42: Implied Share Price | C42: =C40/C41 -> 413.12504
A43: =A21 -> 45917 | B43: Current Share Price | C43: =C22 -> 166
B45: Remaining Upside
B46: Gross Upside | C46: =C42/C43-1 -> 1.488705
B47: MOIC | C47: =C42/C43 -> 2.488705
A48: =(A42-A43)/365 -> 5.290411 | B48: IRR | C48: =C47^(1/A48)-1 -> 0.18808465
B50: Memo: Cash Flows
B51: Cumulative Revenue | C51: =SUM(G76:K76)*1000 -> 855966.06
B52: Cumulative D&A | C52: =SUM(G85:K85)*1000 -> 25137.394
B53: Cumulative EBITDA | C53: =SUM(G86:K86)*1000 -> 210516.31
B54: (-) Interest | C54: 0
A55: 0.2 | B55: (-) Taxes | C55: =-(C53-C52+C54)*A55 -> -37075.783
A56: 0.05 | B56: (-) Capex | C56: =-C51*A56 -> -42798.303
B57: Cumulative Levered FCF | C57: =SUM(C53:C56) -> 130642.22
F58: =F68 -> FY2025A | G58: =G68 -> FY2026E | H58: =H68 -> FY2027E | I58: =I68 -> FY2028E | J58: =J68 -> FY2029E | K58: =K68 -> FY2030E
B59: Current TEV / EBITDA | F59: =$C$28/(F86*1000) -> 12.815645 | G59: =$C$28/(G86*1000) -> 11.06475 | H59: =$C$28/(H86*1000) -> 9.7435285 | I59: =$C$28/(I86*1000) -> 8.8017187 | J59: =$C$28/(J86*1000) -> 7.8388582 | K59: =$C$28/(K86*1000) -> 6.8621759
B61: Illustrative TEV / FY 2026E EBITDA | D61: =E61-2 -> 6 | E61: =F61-2 -> 8 | F61: =G61-2 -> 10 | G61: 12 | H61: =G61+2 -> 14 | I61: =H61+2 -> 16 | J61: =I61+2 -> 18 | K61: =J61+2 -> 20
B62: Implied TEV | D62: =D61*$G$86 -> 196.84651 | E62: =E61*$G$86 -> 262.46202 | F62: =F61*$G$86 -> 328.07752 | G62: =G61*$G$86 -> 393.69302 | H62: =H61*$G$86 -> 459.30853 | I62: =I61*$G$86 -> 524.92403 | J62: =J61*$G$86 -> 590.53954 | K62: =K61*$G$86 -> 656.15504
B63: (-) Net Debt & Other | D63: =-SUM($C$25:$C$27)/1000 -> 13.9178 | E63: =-SUM($C$25:$C$27)/1000 -> 13.9178 | F63: =-SUM($C$25:$C$27)/1000 -> 13.9178 | G63: =-SUM($C$25:$C$27)/1000 -> 13.9178 | H63: =-SUM($C$25:$C$27)/1000 -> 13.9178 | I63: =-SUM($C$25:$C$27)/1000 -> 13.9178 | J63: =-SUM($C$25:$C$27)/1000 -> 13.9178 | K63: =-SUM($C$25:$C$27)/1000 -> 13.9178
B64: Implied Market Cap | D64: =SUM(D62:D63) -> 210.76431 | E64: =SUM(E62:E63) -> 276.37982 | F64: =SUM(F62:F63) -> 341.99532 | G64: =SUM(G62:G63) -> 407.61082 | H64: =SUM(H62:H63) -> 473.22633 | I64: =SUM(I62:I63) -> 538.84183 | J64: =SUM(J62:J63) -> 604.45734 | K64: =SUM(K62:K63) -> 670.07284
B65: Implied Share Price | D65: =D64/($C$23/1000) -> 92.821269 | E65: =E64/($C$23/1000) -> 121.71854 | F65: =F64/($C$23/1000) -> 150.61582 | G65: =G64/($C$23/1000) -> 179.5131 | H65: =H64/($C$23/1000) -> 208.41037 | I65: =I64/($C$23/1000) -> 237.30765 | J65: =J64/($C$23/1000) -> 266.20492 | K65: =K64/($C$23/1000) -> 295.1022
B66: Premium / Discount to Current | D66: =D65/$C$22-1 -> -0.44083573 | E66: =E65/$C$22-1 -> -0.26675575 | F66: =F65/$C$22-1 -> -0.092675782 | G66: =G65/$C$22-1 -> 0.08140419 | H66: =H65/$C$22-1 -> 0.25548416 | I66: =I65/$C$22-1 -> 0.42956413 | J66: =J65/$C$22-1 -> 0.60364411 | K66: =K65/$C$22-1 -> 0.77772408
B68: (USD, FYE March) | C68: FY2022A | D68: FY2023A | E68: FY2024A | F68: FY2025A | G68: FY2026E | H68: FY2027E | I68: FY2028E | J68: FY2029E | K68: FY2030E
B69: Revenue
B70: TTG (Taobao & Tmall Group) | C70: =C4*$C$1 -> 82.8212 | D70: =D4*$C$1 -> 81.58234 | E70: =E4*$C$1 -> 60.88502 | F70: =F4*$C$1 -> 62.97578 | G70: =(1+G89)*F70 -> 66.124569 | H70: =(1+H89)*G70 -> 69.430797 | I70: =(1+I89)*H70 -> 72.902337 | J70: =(1+J89)*I70 -> 76.547454 | K70: =(1+K89)*J70 -> 80.374827
B71: Cloud Intelligence Group | C71: =C5*$C$1 -> 10.43952 | D71: =D5*$C$1 -> 10.80842 | E71: =E5*$C$1 -> 14.89236 | F71: =F5*$C$1 -> 16.52392 | G71: =(1+G90)*F71 -> 19.828704 | H71: =(1+H90)*G71 -> 23.794445 | I71: =(1+I90)*H71 -> 28.553334 | J71: =(1+J90)*I71 -> 34.264001 | K71: =(1+K90)*J71 -> 41.116801
B72: AIDC (International Commerce) | C72: =C6*$C$1 -> 8.55092 | D72: =D6*$C$1 -> 9.68856 | E72: =E6*$C$1 -> 14.36372 | F72: =F6*$C$1 -> 18.522 | G72: =(1+G91)*F72 -> 22.2264 | H72: =(1+H91)*G72 -> 24.44904 | I72: =(1+I91)*H72 -> 26.893944 | J72: =(1+J91)*I72 -> 29.583338 | K72: =(1+K91)*J72 -> 32.541672
B73: Cainiao (Smart Logistics) | C73: =C7*$C$1 -> 6.45498 | D73: =D7*$C$1 -> 7.79534 | E73: =E7*$C$1 -> 13.8628 | F73: =F7*$C$1 -> 14.17808 | G73: =(1+G92)*F73 -> 14.17808 | H73: =(1+H92)*G73 -> 14.17808 | I73: =(1+I92)*H73 -> 14.17808 | J73: =(1+J92)*I73 -> 14.17808 | K73: =(1+K92)*J73 -> 14.17808
B74: Local Services | C74: =C8*$C$1 -> 6.24624 | D74: =D8*$C$1 -> 7.01568 | E74: =E8*$C$1 -> 8.37228 | F74: =F8*$C$1 -> 9.39064 | G74: =(1+G93)*F74 -> 9.39064 | H74: =(1+H93)*G74 -> 9.39064 | I74: =(1+I93)*H74 -> 9.39064 | J74: =(1+J93)*I74 -> 9.39064 | K74: =(1+K93)*J74 -> 9.39064
B75: All Others | C75: =C9*$C$1 -> 4.91582 | D75: =D9*$C$1 -> 4.72584 | E75: =E9*$C$1 -> 19.38734 | F75: =F9*$C$1 -> 17.89816 | G75: =(1+G94)*F75 -> 17.89816 | H75: =(1+H94)*G75 -> 17.89816 | I75: =(1+I94)*H75 -> 17.89816 | J75: =(1+J94)*I75 -> 17.89816 | K75: =(1+K94)*J75 -> 17.89816
B76: Consolidated Total | C76: =SUM(C70:C75) -> 119.42868 | D76: =SUM(D70:D75) -> 121.61618 | E76: =SUM(E70:E75) -> 131.76352 | F76: =SUM(F70:F75) -> 139.48858 | G76: =SUM(G70:G75) -> 149.64655 | H76: =SUM(H70:H75) -> 159.14116 | I76: =SUM(I70:I75) -> 169.8165 | J76: =SUM(J70:J75) -> 181.86167 | K76: =SUM(K70:K75) -> 195.50018
B78: EBITDA
B79: TTG (Taobao & Tmall Group) | C79: =C13*$C$1 -> 25.54034 | D79: =D13*$C$1 -> 25.88068 | E79: =E13*$C$1 -> 27.27578 | F79: =F13*$C$1 -> 27.47248 | G79: =(1+G98)*F79 -> 28.846104 | H79: =(1+H98)*G79 -> 30.288409 | I79: =(1+I98)*H79 -> 31.80283 | J79: =(1+J98)*I79 -> 33.392971 | K79: =(1+K98)*J79 -> 35.06262 | L79: =(K79/F79)^(1/5)-1 -> 0.05
B80: Cloud Intelligence Group | C80: =C14*$C$1 -> 0.16044 | D80: =D14*$C$1 -> 0.19908 | E80: =E14*$C$1 -> 0.85694 | F80: =F14*$C$1 -> 1.47784 | G80: =(1+G99)*F80 -> 2.068976 | H80: =(1+H99)*G80 -> 2.8965664 | I80: =(1+I99)*H80 -> 4.055193 | J80: =(1+J99)*I80 -> 5.6772701 | K80: =(1+K99)*J80 -> 7.9481782 | L80: =(K80/F80)^(1/5)-1 -> 0.4
B81: AIDC (International Commerce) | C81: =C15*$C$1 -> -1.25874 | D81: =D15*$C$1 -> -0.7868 | E81: =E15*$C$1 -> -1.1249 | F81: =F15*$C$1 -> -2.11918 | G81: 0.1 | H81: 2 | I81: =(1+I100)*H81 -> 3 | J81: =(1+J100)*I81 -> 4.5 | K81: =(1+K100)*J81 -> 6.75 | L81: =-(K81/F81)^(1/5)-1 -> 0.2607448
B82: Cainiao (Smart Logistics) | C82: =C16*$C$1 -> -0.2051 | D82: =D16*$C$1 -> -0.05474 | E82: =E16*$C$1 -> 0.19628 | F82: =F16*$C$1 -> 0.04228 | G82: =(1+G101)*F82 -> 0.04228 | H82: =(1+H101)*G82 -> 0.04228 | I82: =(1+I101)*H82 -> 0.04228 | J82: =(1+J101)*I82 -> 0.04228 | K82: =(1+K101)*J82 -> 0.04228 | L82: =(K82/F82)^(1/5)-1 -> 0
B83: Local Services | C83: =C17*$C$1 -> -3.09288 | D83: =D17*$C$1 -> -1.96294 | E83: =E17*$C$1 -> -1.37368 | F83: =F17*$C$1 -> -0.51646 | G83: =(1+G102)*F83 -> -0.51646 | H83: =(1+H102)*G83 -> -0.51646 | I83: =(1+I102)*H83 -> -0.51646 | J83: =(1+J102)*I83 -> -0.51646 | K83: =(1+K102)*J83 -> -0.51646 | L83: =(K83/F83)^(1/5)-1 -> 0
B84: All Others | C84: =C18*$C$1 -> #VALUE! | D84: =D18*$C$1 -> -2.56774 | E84: =E18*$C$1 -> -2.7265 | F84: =F18*$C$1 -> -2.12786 | G84: =(1+G103)*F84 -> -2.12786 | H84: =(1+H103)*G84 -> -2.12786 | I84: =(1+I103)*H84 -> -2.12786 | J84: =(1+J103)*I84 -> -2.12786 | K84: =(1+K103)*J84 -> -2.12786 | L84: =(K84/F84)^(1/5)-1 -> 0
B85: D&A | C85: =27.808*C1 -> 3.89312 | D85: =27.799*C1 -> 3.89186 | E85: =26.64*C1 -> 3.7296 | F85: =29.26*C1 -> 4.0964 | G85: =F85/F76*G76 -> 4.394712 | H85: =G85/G76*H76 -> 4.6735429 | I85: =H85/H76*I76 -> 4.9870483 | J85: =I85/I76*J76 -> 5.3407824 | K85: =J85/J76*K76 -> 5.7413083 | L85: =(K85/F85)^(1/5)-1 -> 0.06984707
B86: Consolidated Total | C86: =SUM(C79:C85) -> #VALUE! | D86: =SUM(D79:D85) -> 24.5994 | E86: =SUM(E79:E85) -> 26.83352 | F86: =SUM(F79:F85) -> 28.3255 | G86: =SUM(G79:G85) -> 32.807752 | H86: =SUM(H79:H85) -> 37.256478 | I86: =SUM(I79:I85) -> 41.243031 | J86: =SUM(J79:J85) -> 46.308984 | K86: =SUM(K79:K85) -> 52.900066 | L86: =(K86/F86)^(1/5)-1 -> 0.13306735
B88: Revenue - YoY Growth %
B89: TTG (Taobao & Tmall Group) | D89: =IFERROR(D70/C70-1,"-") -> -0.014958247 | E89: =IFERROR(E70/D70-1,"-") -> -0.25369853 | F89: =IFERROR(F70/E70-1,"-") -> 0.034339481 | G89: =G98 -> 0.05 | H89: =H98 -> 0.05 | I89: =I98 -> 0.05 | J89: =J98 -> 0.05 | K89: =K98 -> 0.05
B90: Cloud Intelligence Group | D90: =IFERROR(D71/C71-1,"-") -> 0.035336874 | E90: =IFERROR(E71/D71-1,"-") -> 0.37784801 | F90: =IFERROR(F71/E71-1,"-") -> 0.10955685 | G90: 0.2 | H90: 0.2 | I90: 0.2 | J90: 0.2 | K90: 0.2
B91: AIDC (International Commerce) | D91: =IFERROR(D72/C72-1,"-") -> 0.13304299 | E91: =IFERROR(E72/D72-1,"-") -> 0.48254436 | F91: =IFERROR(F72/E72-1,"-") -> 0.28949882 | G91: 0.2 | H91: 0.1 | I91: 0.1 | J91: 0.1 | K91: 0.1
B92: Cainiao (Smart Logistics) | D92: =IFERROR(D73/C73-1,"-") -> 0.20764743 | E92: =IFERROR(E73/D73-1,"-") -> 0.7783445 | F92: =IFERROR(F73/E73-1,"-") -> 0.02274288 | G92: 0 | H92: 0 | I92: 0 | J92: 0 | K92: 0
B93: Local Services | D93: =IFERROR(D74/C74-1,"-") -> 0.12318451 | E93: =IFERROR(E74/D74-1,"-") -> 0.19336686 | F93: =IFERROR(F74/E74-1,"-") -> 0.12163473 | G93: 0 | H93: 0 | I93: 0 | J93: 0 | K93: 0
B94: All Others | D94: =IFERROR(D75/C75-1,"-") -> -0.038646655 | E94: =IFERROR(E75/D75-1,"-") -> 3.1024114 | F94: =IFERROR(F75/E75-1,"-") -> -0.076811981 | G94: 0 | H94: 0 | I94: 0 | J94: 0 | K94: 0
B95: Consolidated Total | D95: =IFERROR(D76/C76-1,"-") -> 0.018316371 | E95: =IFERROR(E76/D76-1,"-") -> 0.083437418 | F95: =IFERROR(F76/E76-1,"-") -> 0.058628215 | G95: =IFERROR(G76/F76-1,"-") -> 0.072822972 | H95: =IFERROR(H76/G76-1,"-") -> 0.063446896 | I95: =IFERROR(I76/H76-1,"-") -> 0.067080903 | J95: =IFERROR(J76/I76-1,"-") -> 0.070930554 | K95: =IFERROR(K76/J76-1,"-") -> 0.074993848
B97: EBITDA - YoY Growth %
B98: TTG (Taobao & Tmall Group) | D98: =IFERROR(D79/C79-1,"-") -> 0.013325586 | E98: =IFERROR(E79/D79-1,"-") -> 0.053905075 | F98: =IFERROR(F79/E79-1,"-") -> 0.0072115261 | G98: 0.05 | H98: 0.05 | I98: 0.05 | J98: 0.05 | K98: 0.05
B99: Cloud Intelligence Group | D99: =IFERROR(D80/C80-1,"-") -> 0.2408377 | E99: =IFERROR(E80/D80-1,"-") -> 3.3045007 | F99: =IFERROR(F80/E80-1,"-") -> 0.72455481 | G99: 0.4 | H99: 0.4 | I99: 0.4 | J99: 0.4 | K99: 0.4
B100: AIDC (International Commerce) | D100: =IFERROR(D81/C81-1,"-") -> -0.37493049 | E100: =IFERROR(E81/D81-1,"-") -> 0.4297153 | F100: =IFERROR(F81/E81-1,"-") -> 0.88388301 | G100: =-IFERROR(G81/F81-1,"-") -> 1.0471881 | H100: =IFERROR(H81/G81-1,"-") -> 19 | I100: 0.5 | J100: 0.5 | K100: 0.5
B101: Cainiao (Smart Logistics) | D101: =IFERROR(D82/C82-1,"-") -> -0.7331058 | E101: =IFERROR(E82/D82-1,"-") -> -4.5856777 | F101: =IFERROR(F82/E82-1,"-") -> -0.78459344 | G101: 0 | H101: 0 | I101: 0 | J101: 0 | K101: 0
B102: Local Services | D102: =IFERROR(D83/C83-1,"-") -> -0.36533587 | E102: =IFERROR(E83/D83-1,"-") -> -0.30019257 | F102: =IFERROR(F83/E83-1,"-") -> -0.6240318 | G102: 0 | H102: 0 | I102: 0 | J102: 0 | K102: 0
B103: All Others | D103: =IFERROR(D84/C84-1,"-") -> - | E103: =IFERROR(E84/D84-1,"-") -> 0.06182869 | F103: =IFERROR(F84/E84-1,"-") -> -0.21956354 | G103: 0 | H103: 0 | I103: 0 | J103: 0 | K103: 0
B104: Consolidated Total | D104: =IFERROR(D86/C86-1,"-") -> - | E104: =IFERROR(E86/D86-1,"-") -> 0.090820101 | F104: =IFERROR(F86/E86-1,"-") -> 0.055601352 | G104: =IFERROR(G86/F86-1,"-") -> 0.15824088 | H104: =IFERROR(H86/G86-1,"-") -> 0.13559986 | I104: =IFERROR(I86/H86-1,"-") -> 0.10700293 | J104: =IFERROR(J86/I86-1,"-") -> 0.12283173 | K104: =IFERROR(K86/J86-1,"-") -> 0.14232838
B106: EBITDA - % Margin
B107: TTG (Taobao & Tmall Group) | C107: =IFERROR(C79/C70,"-") -> 0.30837926 | D107: =IFERROR(D79/D70,"-") -> 0.31723385 | E107: =IFERROR(E79/E70,"-") -> 0.44798836 | F107: =IFERROR(F79/F70,"-") -> 0.43623882 | G107: =IFERROR(G79/G70,"-") -> 0.43623882 | H107: =IFERROR(H79/H70,"-") -> 0.43623882 | I107: =IFERROR(I79/I70,"-") -> 0.43623882 | J107: =IFERROR(J79/J70,"-") -> 0.43623882 | K107: =IFERROR(K79/K70,"-") -> 0.43623882
B108: Cloud Intelligence Group | C108: =IFERROR(C80/C71,"-") -> 0.015368523 | D108: =IFERROR(D80/D71,"-") -> 0.018418973 | E108: =IFERROR(E80/E71,"-") -> 0.057542257 | F108: =IFERROR(F80/F71,"-") -> 0.089436405 | G108: =IFERROR(G80/G71,"-") -> 0.10434247 | H108: =IFERROR(H80/H71,"-") -> 0.12173288 | I108: =IFERROR(I80/I71,"-") -> 0.1420217 | J108: =IFERROR(J80/J71,"-") -> 0.16569198 | K108: =IFERROR(K80/K71,"-") -> 0.19330731
B109: AIDC (International Commerce) | C109: =IFERROR(C81/C72,"-") -> -0.14720521 | D109: =IFERROR(D81/D72,"-") -> -0.081209179 | E109: =IFERROR(E81/E72,"-") -> -0.078315367 | F109: =IFERROR(F81/F72,"-") -> -0.11441421 | G109: =IFERROR(G81/G72,"-") -> 0.0044991542 | H109: =IFERROR(H81/H72,"-") -> 0.081802803 | I109: =IFERROR(I81/I72,"-") -> 0.11154928 | J109: =IFERROR(J81/J72,"-") -> 0.15211265 | K109: =IFERROR(K81/K72,"-") -> 0.20742634
B110: Cainiao (Smart Logistics) | C110: =IFERROR(C82/C73,"-") -> -0.031773917 | D110: =IFERROR(D82/D73,"-") -> -0.007022144 | E110: =IFERROR(E82/E73,"-") -> 0.014158756 | F110: =IFERROR(F82/F73,"-") -> 0.0029820681 | G110: =IFERROR(G82/G73,"-") -> 0.0029820681 | H110: =IFERROR(H82/H73,"-") -> 0.0029820681 | I110: =IFERROR(I82/I73,"-") -> 0.0029820681 | J110: =IFERROR(J82/J73,"-") -> 0.0029820681 | K110: =IFERROR(K82/K73,"-") -> 0.0029820681
B111: Local Services | C111: =IFERROR(C83/C74,"-") -> -0.49515869 | D111: =IFERROR(D83/D74,"-") -> -0.27979326 | E111: =IFERROR(E83/E74,"-") -> -0.16407478 | F111: =IFERROR(F83/F74,"-") -> -0.054997316 | G111: =IFERROR(G83/G74,"-") -> -0.054997316 | H111: =IFERROR(H83/H74,"-") -> -0.054997316 | I111: =IFERROR(I83/I74,"-") -> -0.054997316 | J111: =IFERROR(J83/J74,"-") -> -0.054997316 | K111: =IFERROR(K83/K74,"-") -> -0.054997316
...

Sheet AMZN
A2: =Summary!C7 -> 45917 | B2: Current Capitalization
B3: Current Share Price | F3: =Summary!D7 -> 234.05
B4: Diluted Shares Outstanding | F4: 10.664912
B5: Market Cap | F5: =F3*F4 -> 2496.1227
B6: (+) Net Debt | F6: =F7-F5 -> 66.39
B7: TEV | F7: 2562.5127
B8: 2025E EV / EBITDA | F8: =F7/E53 -> 15.406567
B9: 2026E EV / EBITDA | F9: =F7/F53 -> 12.882062
A11: =Summary!G7 -> 47848 | B11: Exit
B12: 2030E EBITDA | F12: =J53 -> 384.0045
B13: EV / EBITDA | F13: =Summary!H7 -> 15
B14: TEV | F14: =F12*F13 -> 5760.0674
B15: (-) Current Net Debt | F15: =-F6 -> -66.39
B16: (+) Cumulative Levered FCF | F16: =F32 -> 767.50141
B17: Market Cap | F17: =SUM(F14:F16) -> 6461.1788
B18: Current Shares Outstanding | F18: =F4 -> 10.664912
B19: Implied Share Price | F19: =F17/F18 -> 605.83516
B21: Remaining Upside
B22: Gross Upside | F22: =F19/F3-1 -> 1.5884861
B23: MOIC | F23: =F19/F3 -> 2.5884861
A24: =(A11-A2)/365 -> 5.290411 | B24: IRR | F24: =F23^(1/A24)-1 -> 0.19694565
B26: Memo: Cash Flows
B27: Cumulative EBITDA | F27: =SUM(F53:J53) -> 1418.2307
B28: Cumulative D&A | F28: =SUM(F57:J57) -> 635.636
A29: 2.5 | B29: Cumulative Interest Expense | F29: =A29*5 -> 12.5
B30: Cumulative Capex | F30: =SUM(F60:J60) -> 559.96979
A31: 0.1 | B31: Cumulative Taxes | F31: =(F27-F28)*A31 -> 78.259466
B32: Cumulative Levered FCF | F32: =F27-SUM(F29:F31) -> 767.50141
K34: '25E - '30E
C35: 2023A | D35: 2024A | E35: 2025E | F35: 2026E | G35: 2027E | H35: 2028E | I35: 2029E | J35: 2030E | K35: CAGR
B36: Revenue
B37: North America | C37: 353 | D37: 388
B38: International | C38: 131 | D38: 143
B39: AWS | C39: 91 | D39: 108
B40: Total | C40: =SUM(C37:C39) -> 575 | D40: =SUM(D37:D39) -> 639 | E40: 708.046 | F40: 779.6 | G40: 861.758 | H40: =G40*(1+H41) -> 947.9338 | I40: =H40*(1+I41) -> 1042.7272 | J40: =I40*(1+J41) -> 1146.9999 | K40: =(J40/E40)^(1/5)-1 -> 0.10128667
B41: % Growth | D41: =D40/C40-1 -> 0.11130435 | E41: =E40/D40-1 -> 0.10805321 | F41: =F40/E40-1 -> 0.10105841 | G41: =G40/F40-1 -> 0.10538481 | H41: 0.1 | I41: 0.1 | J41: 0.1
B43: Operating Income
B44: North America | C44: 15 | D44: 25
B45: International | C45: -3 | D45: 4
B46: AWS | C46: 25 | D46: 40
B47: Total | C47: =SUM(C44:C46) -> 37 | D47: =SUM(D44:D46) -> 69
B49: EBITDA
B50: North America | C50: =C44/C$47*C$53 -> 34.668243 | D50: =D44/D$47*D$53 -> 43.647826 | E50: =D50*(1+E64) -> 54.559783 | F50: =E50*(1+F64) -> 62.74375 | G50: =F50*(1+G64) -> 72.155312 | H50: =G50*(1+H64) -> 82.978609 | I50: =H50*(1+I64) -> 95.425401 | J50: =I50*(1+J64) -> 109.73921
B51: International | C51: =C45/C$47*C$53 -> -6.9336486 | D51: =D45/D$47*D$53 -> 6.9836522 | E51: =E53-E52-E50 -> 17.486913 | F51: =F53-F52-F50 -> 23.042085 | G51: =G53-G52-G50 -> 26.082489 | H51: =G51*(1+H65) -> 29.994863 | I51: =H51*(1+I65) -> 34.494092 | J51: =I51*(1+J65) -> 39.668206
B52: AWS | C52: =C46/C$47*C$53 -> 57.780405 | D52: =D46/D$47*D$53 -> 69.836522 | E52: =D52*(1+E66) -> 94.279304 | F52: =E52*(1+F66) -> 113.13517 | G52: =F52*(1+G66) -> 135.7622 | H52: =G52*(1+H66) -> 162.91464 | I52: =H52*(1+I66) -> 195.49757 | J52: =I52*(1+J66) -> 234.59708
B53: Total | C53: 85.515 | D53: 120.468 | E53: 166.326 | F53: 198.921 | G53: 234 | H53: =SUM(H50:H52) -> 275.88811 | I53: =SUM(I50:I52) -> 325.41706 | J53: =SUM(J50:J52) -> 384.0045 | K53: =(J53/E53)^(1/5)-1 -> 0.1821572
B54: % Growth | D54: =D53/C53-1 -> 0.40873531 | E54: =E53/D53-1 -> 0.3806654 | F54: =F53/E53-1 -> 0.19597056 | G54: =G53/F53-1 -> 0.17634639 | H54: =H53/G53-1 -> 0.17900902 | I54: =I53/H53-1 -> 0.17952549 | J54: =J53/I53-1 -> 0.180038
B55: % Margin | C55: =C53/C40 -> 0.14872174 | D55: =D53/D40 -> 0.18852582 | E55: =E53/E40 -> 0.23490847 | F55: =F53/F40 -> 0.25515777 | G55: =G53/G40 -> 0.27153795 | H55: =H53/H40 -> 0.29104154 | I55: =I53/I40 -> 0.31208265 | J55: =J53/J40 -> 0.33479035
B57: D&A | C57: 48.515 | D57: 51.468 | E57: 85.326 | F57: 101.921 | G57: 115 | H57: =H58*H40 -> 126.5 | I57: =I58*I40 -> 139.15 | J57: =J58*J40 -> 153.065 | K57: =(J57/E57)^(1/5)-1 -> 0.12398082
B58: % Revenue | C58: =C57/C40 -> 0.084373913 | D58: =D57/D40 -> 0.080544601 | E58: =E57/E40 -> 0.12050912 | F58: =F57/F40 -> 0.13073499 | G58: =G57/G40 -> 0.13344814 | H58: =G58 -> 0.13344814 | I58: =H58 -> 0.13344814 | J58: =I58 -> 0.13344814
B60: Capex | C60: 53 | D60: 83 | E60: 110 | F60: =F61*F40 -> 116.94 | G60: =G61*G40 -> 129.2637 | H60: =H61*H40 -> 94.79338 | I60: =I61*I40 -> 104.27272 | J60: =J61*J40 -> 114.69999 | K60: =(J60/E60)^(1/5)-1 -> 0.0084030227
B61: % Revenue | C61: =C60/C40 -> 0.092173913 | D61: =D60/D40 -> 0.12989045 | E61: =E60/E40 -> 0.15535714 | F61: 0.15 | G61: 0.15 | H61: 0.1 | I61: 0.1 | J61: 0.1
B63: EBITDA - % Growth
B64: North America | D64: =D50/C50-1 -> 0.25901465 | E64: 0.25 | F64: 0.15 | G64: 0.15 | H64: 0.15 | I64: 0.15 | J64: 0.15
B65: International | D65: =-D51/C51-1 -> 0.0072117189 | E65: =E51/D51-1 -> 1.5039782 | F65: =F51/E51-1 -> 0.31767595 | G65: =G51/F51-1 -> 0.13195006 | H65: 0.15 | I65: 0.15 | J65: 0.15
B66: AWS | D66: =D52/C52-1 -> 0.20865406 | E66: 0.35 | F66: 0.2 | G66: 0.2 | H66: 0.2 | I66: 0.2 | J66: 0.2
B67: Total | D67: =D53/C53-1 -> 0.40873531 | E67: =E53/D53-1 -> 0.3806654 | F67: =F53/E53-1 -> 0.19597056 | G67: =G53/F53-1 -> 0.17634639 | H67: =H53/G53-1 -> 0.17900902 | I67: =I53/H53-1 -> 0.17952549 | J67: =J53/I53-1 -> 0.180038

Sheet FOUR
A2: =Summary!C8 -> 46113 | B2: Current Capitalization
B3: Current Share Price | F3: =Summary!D8 -> 42.56
B4: Diluted Shares Outstanding | F4: 73.5
B5: Market Cap | F5: =F3*F4 -> 3128.16
B6: (+) Net Debt | F6: 3500
B7: TEV | F7: 8063.3
B8: 2025E EV / EBITDA | F8: =F7/E41 -> 8.3126804
B9: 2026E EV / EBITDA | F9: =F7/F41 -> 6.7758824
A11: =Summary!G8 -> 47848 | B11: Exit
B12: 2030E EBITDA | F12: =J41 -> 1850
B13: EV / EBITDA | F13: 10
B14: TEV | F14: =F12*F13 -> 18500
B15: (-) Current Net Debt | F15: =-F6 -> -3500
B16: (+) Cumulative Levered FCF | F16: =F32 -> 5879.5515
B17: Market Cap | F17: =SUM(F14:F16) -> 20879.552
B18: Current Shares Outstanding | F18: =F4 -> 73.5
B19: Implied Share Price | F19: =F17/F18 -> 284.07553
B21: Remaining Upside
B22: Gross Upside | F22: =F19/F3-1 -> 5.674707
B23: MOIC | F23: =F19/F3 -> 6.674707
A24: =(A11-A2)/365 -> 4.7534247 | B24: IRR | F24: =F23^(1/A24)-1 -> 0.49086949
B26: Memo: Cash Flows
B27: Cumulative EBITDA | F27: =SUM(F41:J41) -> 8387
B28: Cumulative D&A | F28: =SUM(F45:J45) -> 4635.41
A29: 175 | B29: Cumulative Interest Expense | F29: =A29*5 -> 875
B30: Cumulative Capex | F30: =SUM(F48:J48) -> 1069.71
A31: 0.15 | B31: Cumulative Taxes | F31: =(F27-F28)*A31 -> 562.7385
B32: Cumulative Levered FCF | F32: =F27-SUM(F29:F31) -> 5879.5515
K34: '25E - '30E
C35: 2023A | D35: 2024A | E35: 2025E | F35: 2026E | G35: 2027E | H35: 2028E | I35: 2029E | J35: 2030E | K35: CAGR
B36: Revenue
B37: Total | C37: 2565 | D37: 3331 | E37: 4180 | F37: 5100 | G37: 6120 | H37: 7037 | I37: 8093 | J37: 9307 | K37: =(J37/E37)^(1/5)-1 -> 0.1736178
B38: % Growth | D38: =D37/C37-1 -> 0.29863548 | E38: =E37/D37-1 -> 0.25487841 | F38: =F37/E37-1 -> 0.22009569 | G38: =G37/F37-1 -> 0.2 | H38: 0.15 | I38: 0.15 | J38: 0.15
B40: EBITDA
B41: Total | C41: 376 | D41: 542 | E41: 970 | F41: 1190 | G41: 1580 | H41: 1777 | I41: 1990 | J41: 1850 | K41: =(J41/E41)^(1/5)-1 -> 0.13783686
B42: % Growth | D42: =D41/C41-1 -> 0.44148936 | E42: =E41/D41-1 -> 0.7896679 | F42: =F41/E41-1 -> 0.22680412 | G42: =G41/F41-1 -> 0.32773109 | H42: =H41/G41-1 -> 0.12468354 | I42: =I41/H41-1 -> 0.11986494 | J42: =J41/I41-1 -> -0.070351759
B43: % Margin | C43: =C41/C37 -> 0.14658869 | D43: =D41/D37 -> 0.1627139 | E43: =E41/E37 -> 0.23205742 | F43: =F41/F37 -> 0.23333333 | G43: =G41/G37 -> 0.25816993 | H43: =H41/H37 -> 0.25252238 | I43: =I41/I37 -> 0.24589151 | J43: =J41/J37 -> 0.19877512
B45: D&A | C45: 196 | D45: 271 | E45: 523 | F45: =F46*F37 -> 663 | G45: =G46*G37 -> 795.6 | H45: =H46*H37 -> 914.81 | I45: =I46*I37 -> 1052.09 | J45: =J46*J37 -> 1209.91 | K45: =(J45/E45)^(1/5)-1 -> 0.18263377
B46: % Revenue | C46: =C45/C37 -> 0.076413255 | D46: =D45/D37 -> 0.08135695 | E46: =E45/E37 -> 0.12511962 | F46: 0.13 | G46: 0.13 | H46: 0.13 | I46: 0.13 | J46: 0.13
B48: Capex | C48: 92 | D48: 108 | E48: 115 | F48: =F49*F37 -> 153 | G48: =G49*G37 -> 183.6 | H48: =H49*H37 -> 211.11 | I48: =I49*I37 -> 242.79 | J48: =J49*J37 -> 279.21 | K48: =(J48/E48)^(1/5)-1 -> 0.1941163
B49: % Revenue | C49: =C48/C37 -> 0.035867446 | D49: =D48/D37 -> 0.032422696 | E49: =E48/E37 -> 0.027511962 | F49: 0.03 | G49: 0.03 | H49: 0.03 | I49: 0.03 | J49: 0.03
A52: Position Summary (April 2026)
B53: Entry Price | F53: 42.56
B54: Entry Date | F54: 46113
B55: Thesis | F55: Quasi-LBO: fixed debt, growing FCF, equity absorbs disproportionate EV creation. 12% EBITDA CAGR, 10x exit, $255+ target.

Sheet WBD
B2: Current Capitalization
A3: =Summary!C9 -> 45917 | B3: Current Share Price | C3: =Summary!D9 -> 18
B4: (x) FDSO | C4: 2534.6633
B5: Market Cap | C5: =C3*C4 -> 45623.939
B6: (+) Net Debt | C6: 33578
B7: TEV | C7: =C5+C6 -> 79201.939
B8: 2025E EV / EBITDA | C8: =C7/F38 -> 8.9869441
B9: 2026E EV / EBITDA | C9: =C7/G38 -> 8.7111679
B11: Exit
A12: =Summary!G9 -> 47848 | B12: 2030E EBITDA | C12: =K38 -> 10549.584
B13: EV / EBITDA | C13: =Summary!H9 -> 10
B14: TEV | C14: =C12*C13 -> 105495.84
B15: (-) Net Debt | C15: =-K40 -> -12947
B16: Market Cap | C16: =C14+C15 -> 92548.839
B17: (/) FDSO | C17: =C4 -> 2534.6633
B18: Implied Share Price | C18: =C16/C17 -> 36.513268
B20: Remaining Upside
B21: Gross Upside | C21: =C18/C3-1 -> 1.0285149
B22: MOIC | C22: =C18/C3 -> 2.0285149
A23: =(A12-A3)/365 -> 5.290411 | B23: IRR | C23: =C22^(1/A23)-1 -> 0.14304467
C25: 2022A | D25: 2023A | E25: 2024A | F25: 2025E | G25: 2026E | H25: 2027E | I25: 2028E | J25: 2029E | K25: 2030E
B26: Revenue
B27: Studios | C27: 13798 | D27: 12192 | E27: 11607 | F27: 12126 | G27: 12445 | H27: =G27*(1+H57) -> 12818.35 | I27: =H27*(1+I57) -> 13202.9 | J27: =I27*(1+J57) -> 13598.988 | K27: =J27*(1+K57) -> 14006.957
B28: Networks | C28: 23186 | D28: 21244 | E28: 20175 | F28: 17153 | G28: 14917 | H28: =G28*(1+H58) -> 13425.3 | I28: =H28*(1+I58) -> 12082.77 | J28: =I28*(1+J58) -> 10874.493 | K28: =J28*(1+K58) -> 9787.0437
B29: DTC | C29: 9693 | D29: 10154 | E29: 10313 | F29: 11023 | G29: 11992 | H29: =G29*(1+H59) -> 13591.981 | I29: =H29*(1+I59) -> 15469.302 | J29: =I29*(1+J59) -> 17681.243 | K29: =J29*(1+K59) -> 20297.94
B30: Elims and Adj. | C30: =C31-SUM(C27:C29) -> -3582 | D30: =D31-SUM(D27:D29) -> -2269 | E30: =E31-SUM(E27:E29) -> -2774 | F30: =F31-SUM(F27:F29) -> -2639 | G30: =G31-SUM(G27:G29) -> -2679 | H30: =G30*(1+H60) -> -2679 | I30: =H30*(1+I60) -> -2679 | J30: =I30*(1+J60) -> -2679 | K30: =J30*(1+K60) -> -2679
B31: Total Revenue | C31: 43095 | D31: 41321 | E31: 39321 | F31: 37663 | G31: 36675 | H31: =SUM(H27:H30) -> 37156.631 | I31: =SUM(I27:I30) -> 38075.972 | J31: =SUM(J27:J30) -> 39475.724 | K31: =SUM(K27:K30) -> 41412.941
B33: Adj. EBITDA
B34: Studios | C34: 2749 | D34: 2183 | E34: 1652 | F34: 2028 | G34: 2463 | H34: =G34*(1+H64) -> 2709.3 | I34: =H34*(1+I64) -> 2980.23 | J34: =I34*(1+J64) -> 3278.253 | K34: =J34*(1+K64) -> 3606.0783
B35: Networks | C35: 7465 | D35: 9063 | E35: 8149 | F35: 7012 | G35: 6662 | H35: =G35*(1+H65) -> 6328.9 | I35: =H35*(1+I65) -> 6012.455 | J35: =I35*(1+J65) -> 5711.8323 | K35: =J35*(1+K65) -> 5426.2406
B36: DTC | C36: -1409 | D36: 103 | E36: 677 | F36: 1313 | G36: =F36+(G115/1000) -> 1779.3008 | H36: =G36+(H115/1000) -> 2034.6462 | I36: =H36+(I115/1000) -> 2366.9182 | J36: =I36+(J115/1000) -> 2792.1103 | K36: =J36+(K115/1000) -> 3329.5657
B37: Elims and Adj. | C37: =C38-SUM(C34:C36) -> -2012 | D37: =D38-SUM(D34:D36) -> -1149 | E37: =E38-SUM(E34:E36) -> -1446 | F37: =F38-SUM(F34:F36) -> -1540 | G37: =G38-SUM(G34:G36) -> -1812.3008 | H37: =G37*(1+H67) -> -1812.3008 | I37: =H37*(1+I67) -> -1812.3008 | J37: =I37*(1+J67) -> -1812.3008 | K37: =J37*(1+K67) -> -1812.3008
B38: Total Adj. EBITDA | C38: 6793 | D38: 10200 | E38: 9032 | F38: 8813 | G38: 9092 | H38: =SUM(H34:H37) -> 9260.5454 | I38: =SUM(I34:I37) -> 9547.3024 | J38: =SUM(J34:J37) -> 9969.8948 | K38: =SUM(K34:K37) -> 10549.584
A40: 3000 | B40: Net Debt | C40: 45268 | D40: 39889 | E40: 34193 | F40: 29811 | G40: 24947 | H40: =G40-$A$40 -> 21947 | I40: =H40-$A$40 -> 18947 | J40: =I40-$A$40 -> 15947 | K40: =J40-$A$40 -> 12947
B41: Net Leverage | C41: =C40/C38 -> 6.6639187 | D41: =D40/D38 -> 3.9106863 | E41: =E40/E38 -> 3.7857617 | F41: =F40/F38 -> 3.3826166 | G41: =G40/G38 -> 2.7438407 | H41: =H40/H38 -> 2.3699468 | I41: =I40/I38 -> 1.9845396 | J41: =J40/J38 -> 1.5995154 | K41: =K40/K38 -> 1.2272522
B43: DTC
B44: Domestic Subscribers | C44: 54600 | D44: 52000 | E44: 57100 | F44: 56850 | G44: 57600 | H44: =G44*(1+H92) -> 60480 | I44: =H44*(1+I92) -> 63504 | J44: =I44*(1+J92) -> 66679.2 | K44: =J44*(1+K92) -> 70013.16
B45: International Subscribers | C45: 42300 | D45: 45600 | E45: 59800 | F45: 70800 | G45: 92800 | H45: =G45*(1+H93) -> 111360 | I45: =H45*(1+I93) -> 133632 | J45: =I45*(1+J93) -> 160358.4 | K45: =J45*(1+K93) -> 192430.08
B46: Total DTC Subscribers | C46: =SUM(C44:C45) -> 96900 | D46: =SUM(D44:D45) -> 97600 | E46: =SUM(E44:E45) -> 116900 | F46: =SUM(F44:F45) -> 127650 | G46: =SUM(G44:G45) -> 150400 | H46: =SUM(H44:H45) -> 171840 | I46: =SUM(I44:I45) -> 197136 | J46: =SUM(J44:J45) -> 227037.6 | K46: =SUM(K44:K45) -> 262443.24
B48: Domestic DTC ARPU | C48: 10.63 | D48: 11.21 | E48: 11.89 | F48: 11.65 | G48: 11.65 | H48: =G48*(1+H96) -> 11.9995 | I48: =H48*(1+I96) -> 12.359485 | J48: =I48*(1+J96) -> 12.73027 | K48: =J48*(1+K96) -> 13.112178
B49: International DTC ARPU | C49: 3.7 | D49: 3.7 | E49: 3.85 | F49: 3.66 | G49: 3.66 | H49: =G49*(1+H97) -> 3.7698 | I49: =H49*(1+I97) -> 3.882894 | J49: =I49*(1+J97) -> 3.9993808 | K49: =J49*(1+K97) -> 4.1193622
B50: Total Blended ARPU | C50: =C54/C46 -> 91.257957 | D50: =D54/D46 -> 92.414754 | E50: =E54/E46 -> 93.325817 | F50: =F54/F46 -> 86.620964 | G50: =G54/G46 -> 80.64 | H50: =H54/H46 -> 79.995439 | I50: =I54/I46 -> 79.361799 | J50: =J54/J46 -> 78.76291 | K50: =K54/K46 -> 78.220991
B52: Domestic DTC Revenue | C52: =C44*C48*12 -> 6964776 | D52: =D44*D48*12 -> 6995040 | E52: =E44*E48*12 -> 8147028 | F52: =F44*F48*12 -> 7947630 | G52: =G44*G48*12 -> 8052480 | H52: =H44*H48*12 -> 8708757.1 | I52: =I44*I48*12 -> 9418520.8 | J52: =J44*J48*12 -> 10186130 | K52: =K44*K48*12 -> 11016300
B53: International DTC Revenue | C53: =C45*C49*12 -> 1878120 | D53: =D45*D49*12 -> 2024640 | E53: =E45*E49*12 -> 2762760 | F53: =F45*F49*12 -> 3109536 | G53: =G45*G49*12 -> 4075776 | H53: =H45*H49*12 -> 5037659.1 | I53: =I45*I49*12 -> 6226546.7 | J53: =J45*J49*12 -> 7696011.7 | K53: =K45*K49*12 -> 9512270.5
B54: Total DTC Revenue | C54: =SUM(C52:C53) -> 8842896 | D54: =SUM(D52:D53) -> 9019680 | E54: =SUM(E52:E53) -> 10909788 | F54: =SUM(F52:F53) -> 11057166 | G54: =SUM(G52:G53) -> 12128256 | H54: =SUM(H52:H53) -> 13746416 | I54: =SUM(I52:I53) -> 15645068 | J54: =SUM(J52:J53) -> 17882142 | K54: =SUM(K52:K53) -> 20528570
B56: Revenue - YoY Growth %
B57: Studios | D57: =D27/C27-1 -> -0.11639368 | E57: =E27/D27-1 -> -0.047982283 | F57: =F27/E27-1 -> 0.044714396 | G57: =G27/F27-1 -> 0.026307109 | H57: 0.03 | I57: 0.03 | J57: 0.03 | K57: 0.03
B58: Networks | D58: =D28/C28-1 -> -0.08375744 | E58: =E28/D28-1 -> -0.05032009 | F58: =F28/E28-1 -> -0.14978934 | G58: =G28/F28-1 -> -0.13035621 | H58: -0.1 | I58: -0.1 | J58: -0.1 | K58: -0.1
B59: DTC | D59: =D29/C29-1 -> 0.047560095 | E59: =E29/D29-1 -> 0.015658854 | F59: =F29/E29-1 -> 0.068845147 | G59: =G29/F29-1 -> 0.087907103 | H59: =H102 -> 0.13342069 | I59: =I102 -> 0.13811973 | J59: =J102 -> 0.14298912 | K59: =K102 -> 0.14799281
B60: Elims and Adj. | D60: =D30/C30-1 -> -0.366555 | E60: =E30/D30-1 -> 0.22256501 | F60: =F30/E30-1 -> -0.048666186 | G60: =G30/F30-1 -> 0.015157257 | H60: 0 | I60: 0 | J60: 0 | K60: 0
B61: Total Revenue | D61: =D31/C31-1 -> -0.041164868 | E61: =E31/D31-1 -> -0.048401539 | F61: =F31/E31-1 -> -0.042165764 | G61: =G31/F31-1 -> -0.026232642 | H61: =H31/G31-1 -> 0.013132403 | I61: =I31/H31-1 -> 0.024742318 | J61: =J31/I31-1 -> 0.036762078 | K61: =K31/J31-1 -> 0.049073632
B63: Adj. EBITDA - YoY Growth %
B64: Studios | D64: =D34/C34-1 -> -0.20589305 | E64: =E34/D34-1 -> -0.24324324 | F64: =F34/E34-1 -> 0.22760291 | G64: =G34/F34-1 -> 0.21449704 | H64: 0.1 | I64: 0.1 | J64: 0.1 | K64: 0.1
B65: Networks | D65: =D35/C35-1 -> 0.21406564 | E65: =E35/D35-1 -> -0.10084961 | F65: =F35/E35-1 -> -0.13952632 | G65: =G35/F35-1 -> -0.049914432 | H65: -0.05 | I65: -0.05 | J65: -0.05 | K65: -0.05
B66: DTC | D66: =D36/C36-1 -> -1.0731015 | E66: =E36/D36-1 -> 5.5728155 | F66: =F36/E36-1 -> 0.9394387 | G66: =G36/F36-1 -> 0.35514151 | H66: =H36/G36-1 -> 0.14350887 | I66: =I36/H36-1 -> 0.163307 | J66: =J36/I36-1 -> 0.17963955 | K66: =K36/J36-1 -> 0.19249075
B67: Elims and Adj. | D67: =D37/C37-1 -> -0.42892644 | E67: =E37/D37-1 -> 0.25848564 | F67: =F37/E37-1 -> 0.065006916 | G67: =G37/F37-1 -> 0.1768187 | H67: 0 | I67: 0 | J67: 0 | K67: 0
B68: Total Adj. EBITDA | D68: =D38/C38-1 -> 0.50154571 | E68: =E38/D38-1 -> -0.1145098 | F68: =F38/E38-1 -> -0.024247121 | G68: =G38/F38-1 -> 0.031657778 | H68: =H38/G38-1 -> 0.018537774 | I68: =I38/H38-1 -> 0.030965452 | J68: =J38/I38-1 -> 0.044263013 | K68: =K38/J38-1 -> 0.058143954
B70: Adj. EBITDA Margin %
B71: Studios | C71: =C34/C27 -> 0.19923177 | D71: =D34/D27 -> 0.17905184 | E71: =E34/E27 -> 0.14232791 | F71: =F34/F27 -> 0.16724394 | G71: =G34/G27 -> 0.19791081 | H71: =H34/H27 -> 0.21136106 | I71: =I34/I27 -> 0.2257254 | J71: =J34/J27 -> 0.24106596 | K71: =K34/K27 -> 0.25744909
B72: Networks | C72: =C35/C28 -> 0.32196153 | D72: =D35/D28 -> 0.42661457 | E72: =E35/E28 -> 0.40391574 | F72: =F35/F28 -> 0.40879147 | G72: =G35/G28 -> 0.44660455 | H72: =H35/H28 -> 0.47141591 | I72: =I35/I28 -> 0.49760568 | J72: =J35/J28 -> 0.52525044 | K72: =K35/K28 -> 0.55443102
B73: DTC | C73: =C36/C29 -> -0.14536263 | D73: =D36/D29 -> 0.010143786 | E73: =E36/E29 -> 0.065645302 | F73: =F36/F29 -> 0.11911458 | G73: =G36/G29 -> 0.14837398 | H73: =H36/H29 -> 0.14969461 | I73: =I36/I29 -> 0.15300744 | J73: =J36/J29 -> 0.15791369 | K73: =K36/K29 -> 0.16403466
B74: Elims and Adj. | C74: =C37/C30 -> 0.56169738 | D74: =D37/D30 -> 0.50639048 | E74: =E37/E30 -> 0.52126893 | F74: =F37/F30 -> 0.58355438 | G74: =G37/G30 -> 0.67648406 | H74: =H37/H30 -> 0.67648406 | I74: =I37/I30 -> 0.67648406 | J74: =J37/J30 -> 0.67648406 | K74: =K37/K30 -> 0.67648406
B75: Total Adj. EBITDA | C75: =C38/C31 -> 0.1576285 | D75: =D38/D31 -> 0.24684785 | E75: =E38/E31 -> 0.22969914 | F75: =F38/F31 -> 0.23399623 | G75: =G38/G31 -> 0.24790729 | H75: =H38/H31 -> 0.24922995 | I75: =I38/I31 -> 0.2507435 | J75: =J38/J31 -> 0.25255762 | K75: =K38/K31 -> 0.25474124
B77: Revenue - % of Total
B78: Studios | C78: =C27/C$31 -> 0.32017635 | D78: =D27/D$31 -> 0.29505578 | E78: =E27/E$31 -> 0.29518578 | F78: =F27/F$31 -> 0.32196054 | G78: =G27/G$31 -> 0.33933197 | H78: =H27/H$31 -> 0.34498149 | I78: =I27/I$31 -> 0.3467515 | J78: =J27/J$31 -> 0.34448988 | K78: =K27/K$31 -> 0.33822657
B79: Networks | C79: =C28/C$31 -> 0.53802065 | D79: =D28/D$31 -> 0.51412115 | E79: =E28/E$31 -> 0.51308461 | F79: =F28/F$31 -> 0.45543371 | G79: =G28/G$31 -> 0.40673483 | H79: =H28/H$31 -> 0.3613164 | I79: =I28/I$31 -> 0.3173332 | J79: =J28/J$31 -> 0.27547292 | K79: =K28/K$31 -> 0.23632815
B80: DTC | C80: =C29/C$31 -> 0.22492168 | D80: =D29/D$31 -> 0.24573461 | E80: =E29/E$31 -> 0.26227715 | F80: =F29/F$31 -> 0.29267451 | G80: =G29/G$31 -> 0.32698023 | H80: =H29/H$31 -> 0.3658023 | I80: =I29/I$31 -> 0.40627463 | J80: =J29/J$31 -> 0.44790169 | K80: =K29/K$31 -> 0.4901352
B81: Elims and Adj. | C81: =C30/C$31 -> -0.083118691 | D81: =D30/D$31 -> -0.054911546 | E81: =E30/E$31 -> -0.070547545 | F81: =F30/F$31 -> -0.070068768 | G81: =G30/G$31 -> -0.073047035 | H81: =H30/H$31 -> -0.072100186 | I81: =I30/I$31 -> -0.070359333 | J81: =J30/J$31 -> -0.067864493 | K81: =K30/K$31 -> -0.064689924
B82: Total Revenue | C82: =C31/C$31 -> 1 | D82: =D31/D$31 -> 1 | E82: =E31/E$31 -> 1 | F82: =F31/F$31 -> 1 | G82: =G31/G$31 -> 1 | H82: =H31/H$31 -> 1 | I82: =I31/I$31 -> 1 | J82: =J31/J$31 -> 1 | K82: =K31/K$31 -> 1
B84: Adj. EBITDA - % of Total
B85: Studios | C85: =C34/C$38 -> 0.40468129 | D85: =D34/D$38 -> 0.21401961 | E85: =E34/E$38 -> 0.18290523 | F85: =F34/F$38 -> 0.2301146 | G85: =G34/G$38 -> 0.27089749 | H85: =H34/H$38 -> 0.29256376 | I85: =I34/I$38 -> 0.31215414 | J85: =J34/J$38 -> 0.32881521 | K85: =K34/K$38 -> 0.34182185
B86: Networks | C86: =C35/C$38 -> 1.0989254 | D86: =D35/D$38 -> 0.88852941 | E86: =E35/E$38 -> 0.90223649 | F86: =F35/F$38 -> 0.7956428 | G86: =G35/G$38 -> 0.73273207 | H86: =H35/H$38 -> 0.68342627 | I86: =I35/I$38 -> 0.62975433 | J86: =J35/J$38 -> 0.57290798 | K86: =K35/K$38 -> 0.51435589
B87: DTC | C87: =C36/C$38 -> -0.2074194 | D87: =D36/D$38 -> 0.010098039 | E87: =E36/E$38 -> 0.074955713 | F87: =F36/F$38 -> 0.14898445 | G87: =G36/G$38 -> 0.1956996 | H87: =H36/H$38 -> 0.21971127 | I87: =I36/I$38 -> 0.24791487 | J87: =J36/J$38 -> 0.28005414 | K87: =K36/K$38 -> 0.3156111
B88: Elims and Adj. | C88: =C37/C$38 -> -0.29618725 | D88: =D37/D$38 -> -0.11264706 | E88: =E37/E$38 -> -0.16009743 | F88: =F37/F$38 -> -0.17474186 | G88: =G37/G$38 -> -0.19932917 | H88: =H37/H$38 -> -0.1957013 | I88: =I37/I$38 -> -0.18982334 | J88: =J37/J$38 -> -0.18177732 | K88: =K37/K$38 -> -0.17178884
B89: Total Adj. EBITDA | C89: =C38/C$38 -> 1 | D89: =D38/D$38 -> 1 | E89: =E38/E$38 -> 1 | F89: =F38/F$38 -> 1 | G89: =G38/G$38 -> 1 | H89: =H38/H$38 -> 1 | I89: =I38/I$38 -> 1 | J89: =J38/J$38 -> 1 | K89: =K38/K$38 -> 1
B91: DTC - YoY Growth %
B92: Domestic Subscribers | D92: =D44/C44-1 -> -0.047619048 | E92: =E44/D44-1 -> 0.098076923 | F92: =F44/E44-1 -> -0.0043782837 | G92: =G44/F44-1 -> 0.013192612 | H92: 0.05 | I92: 0.05 | J92: 0.05 | K92: 0.05
B93: International Subscribers | D93: =D45/C45-1 -> 0.078014184 | E93: =E45/D45-1 -> 0.31140351 | F93: =F45/E45-1 -> 0.18394649 | G93: =G45/F45-1 -> 0.31073446 | H93: 0.2 | I93: 0.2 | J93: 0.2 | K93: 0.2
B94: Total DTC Subscribers | D94: =D46/C46-1 -> 0.0072239422 | E94: =E46/D46-1 -> 0.1977459 | F94: =F46/E46-1 -> 0.091958939 | G94: =G46/F46-1 -> 0.1782217 | H94: =H46/G46-1 -> 0.14255319 | I94: =I46/H46-1 -> 0.1472067 | J94: =J46/I46-1 -> 0.15168006 | K94: =K46/J46-1 -> 0.15594615
B96: Domestic DTC ARPU | D96: =D48/C48-1 -> 0.054562559 | E96: =E48/D48-1 -> 0.060660125 | F96: =F48/E48-1 -> -0.020185029 | G96: =G48/F48-1 -> 0 | H96: 0.03 | I96: 0.03 | J96: 0.03 | K96: 0.03
B97: International DTC ARPU | D97: =D49/C49-1 -> 0 | E97: =E49/D49-1 -> 0.040540541 | F97: =F49/E49-1 -> -0.049350649 | G97: =G49/F49-1 -> 0 | H97: 0.03 | I97: 0.03 | J97: 0.03 | K97: 0.03
B98: Total Blended ARPU | D98: =D50/C50-1 -> 0.012676127 | E98: =E50/D50-1 -> 0.0098584133 | F98: =F50/E50-1 -> -0.0718435 | G98: =G50/F50-1 -> -0.06904753 | H98: =H50/G50-1 -> -0.0079930666 | I98: =I50/H50-1 -> -0.0079209586 | J98: =J50/I50-1 -> -0.0075463115 | K98: =K50/J50-1 -> -0.0068803767
B100: Domestic DTC Revenue | D100: =D52/C52-1 -> 0.0043452941 | E100: =E52/D52-1 -> 0.16468641 | F100: =F52/E52-1 -> -0.024474937 | G100: =G52/F52-1 -> 0.013192612 | H100: =H52/G52-1 -> 0.0815 | I100: =I52/H52-1 -> 0.0815 | J100: =J52/I52-1 -> 0.0815 | K100: =K52/J52-1 -> 0.0815
B101: International DTC Revenue | D101: =D53/C53-1 -> 0.078014184 | E101: =E53/D53-1 -> 0.36456852 | F101: =F53/E53-1 -> 0.12551796 | G101: =G53/F53-1 -> 0.31073446 | H101: =H53/G53-1 -> 0.236 | I101: =I53/H53-1 -> 0.236 | J101: =J53/I53-1 -> 0.236 | K101: =K53/J53-1 -> 0.236
B102: Total DTC Revenue | D102: =D54/C54-1 -> 0.019991641 | E102: =E54/D54-1 -> 0.20955378 | F102: =F54/E54-1 -> 0.013508787 | G102: =G54/F54-1 -> 0.096868402 | H102: =H54/G54-1 -> 0.13342069 | I102: =I54/H54-1 -> 0.13811973 | J102: =J54/I54-1 -> 0.14298912 | K102: =K54/J54-1 -> 0.14799281
B104: New DTC Subscribers | G104: =G46-F46 -> 22750 | H104: =H46-G46 -> 21440 | I104: =I46-H46 -> 25296 | J104: =J46-I46 -> 29901.6 | K104: =K46-J46 -> 35405.64
B105: ARPU | G105: =G50 -> 80.64 | H105: =H50 -> 79.995439 | I105: =I50 -> 79.361799 | J105: =J50 -> 78.76291 | K105: =K50 -> 78.220991
B106: New Revenue | G106: =G104*G105 -> 1834560 | H106: =H104*H105 -> 1715102.2 | I106: =I104*I105 -> 2007536.1 | J106: =J104*J105 -> 2355137 | K106: =K104*K105 -> 2769464.3
B108: Existing DTC Subscribers | G108: =G46 -> 150400 | H108: =H46 -> 171840 | I108: =I46 -> 197136 | J108: =J46 -> 227037.6 | K108: =K46 -> 262443.24
B109: % Churn | G109: 0.1 | H109: 0.1 | I109: 0.1 | J109: 0.1 | K109: 0.1
B110: ARPU | G110: =G105 -> 80.64 | H110: =H105 -> 79.995439 | I110: =I105 -> 79.361799 | J110: =J105 -> 78.76291 | K110: =K105 -> 78.220991
B111: Lost Revenue | G111: =-G108*G109*G110 -> -1212825.6 | H111: =-H108*H109*H110 -> -1374641.6 | I111: =-I108*I109*I110 -> -1564506.8 | J111: =-J108*J109*J110 -> -1788214.2 | K111: =-K108*K109*K110 -> -2052857
B113: Net DTC Revenue | G113: =G106+G111 -> 621734.4 | H113: =H106+H111 -> 340460.59 | I113: =I106+I111 -> 443029.3 | J113: =J106+J111 -> 566922.82 | K113: =K106+K111 -> 716607.22
B114: DTC Drop-Through to EBITDA | G114: 0.75 | H114: 0.75 | I114: 0.75 | J114: 0.75 | K114: 0.75
B115: Implied EBITDA Uplift | G115: =G113*G114 -> 466300.8 | H115: =H113*H114 -> 255345.44 | I115: =I113*I114 -> 332271.98 | J115: =J113*J114 -> 425192.12 | K115: =K113*K114 -> 537455.41

Sheet XPOF
A2: =Summary!C10 -> 46113 | B2: Current Capitalization
B3: Current Share Price | F3: =Summary!D10 -> 8.41
B4: Diluted Shares Outstanding | F4: 49.144444
B5: Market Cap | F5: =F3*F4 -> 413.30478
B6: (+) Net Debt & NCI | F6: 271.6
B7: TEV | F7: =SUM(F5:F6) -> 684.90478
B8: 2025E EV / EBITDA | C8: =C7/F35 -> #DIV/0! | F8: =F7/G66 -> 6.2264071
B9: 2026E EV / EBITDA | C9: =C7/G35 -> #DIV/0! | F9: =F7/H66 -> 5.7866372
A11: =Summary!G10 -> 47848 | B11: Exit
B12: 2030E EBITDA | F12: =L66 -> 178.15627
B13: EV / EBITDA | F13: =Summary!H10 -> 8
B14: TEV | F14: =F12*F13 -> 1425.2502
B15: (-) Current Net Debt & NCI | F15: =-F6 -> -271.6
B16: (+) Cumulative Levered FCF | F16: =F32 -> 335.29828
B17: Market Cap | F17: =SUM(F14:F16) -> 1488.9484
B18: Current Shares Outstanding | F18: =F4 -> 49.144444
B19: Implied Share Price | F19: =F17/F18 -> 30.297391
B21: Remaining Upside
B22: Gross Upside | C22: =C18/C19-1 -> #DIV/0! | F22: =F19/F3-1 -> 2.6025435
B23: MOIC | C23: =C18/C19 -> #DIV/0! | F23: =F19/F3 -> 3.6025435
A24: =(A11-A2)/365 -> 4.7534247 | B24: IRR | C24: =C23^(1/A24)-1 -> #DIV/0! | F24: =F23^(1/A24)-1 -> 0.30947276
B26: Memo: Cash Flows
B27: Cumulative EBITDA | F27: =SUM(H66:L66) -> 726.54557
A28: 0.2 | B28: Cumulative D&A | F28: =A28*F27 -> 145.30911
A29: 50 | B29: Cumulative Interest Expense | F29: =A29*5 -> 250
A30: 5 | B30: Cumulative Capex | F30: =A30*5 -> 25
A31: 0.2 | B31: Cumulative Taxes | F31: =(F27-F28)*A31 -> 116.24729
B32: Cumulative Levered FCF | F32: =F27-SUM(F29:F31) -> 335.29828
B34: ($ in millions except per unit) | C34: 2021A | D34: 2022A | E34: 2023A | F34: 2024A | G34: 2025E | H34: 2026E | I34: 2027E | J34: 2028E | K34: 2029E | L34: 2030E | M34: '25E - '30E CAGR
B35: Studios
B36: Club Pilates | C36: 726 | D36: 953 | E36: 1109 | F36: 1200 | G36: =MROUND((1+G83)*F36,1) -> 1320 | H36: =MROUND((1+H83)*G36,1) -> 1452 | I36: =MROUND((1+I83)*H36,1) -> 1597 | J36: =MROUND((1+J83)*I36,1) -> 1757 | K36: =MROUND((1+K83)*J36,1) -> 1933 | L36: =MROUND((1+L83)*K36,1) -> 2126 | M36: =(L36/G36)^(1/5)-1 -> 0.10001312
B37: StretchLab | C37: 193 | D37: 358 | E37: 470 | F37: 529 | G37: =MROUND((1+G84)*F37,1) -> 582 | H37: =MROUND((1+H84)*G37,1) -> 611 | I37: =MROUND((1+I84)*H37,1) -> 642 | J37: =MROUND((1+J84)*I37,1) -> 674 | K37: =MROUND((1+K84)*J37,1) -> 708 | L37: =MROUND((1+L84)*K37,1) -> 743 | M37: =(L37/G37)^(1/5)-1 -> 0.050057705
B38: Pure Barre | C38: 591 | D38: 624 | E38: 634 | F38: 626 | G38: =MROUND((1+G85)*F38,1) -> 620 | H38: =MROUND((1+H85)*G38,1) -> 614 | I38: =MROUND((1+I85)*H38,1) -> 608 | J38: =MROUND((1+J85)*I38,1) -> 602 | K38: =MROUND((1+K85)*J38,1) -> 596 | L38: =MROUND((1+L85)*K38,1) -> 590 | M38: =(L38/G38)^(1/5)-1 -> -0.0098703534
B39: YogaSix | C39: 109 | D39: 178 | E39: 191 | F39: 194 | G39: =G40-SUM(G36:G38) -> 197 | H39: =MROUND((1+H86)*G39,1) -> 200 | I39: =MROUND((1+I86)*H39,1) -> 203 | J39: =MROUND((1+J86)*I39,1) -> 206 | K39: =MROUND((1+K86)*J39,1) -> 209 | L39: =MROUND((1+L86)*K39,1) -> 212 | M39: =(L39/G39)^(1/5)-1 -> 0.014784738
B40: Total | C40: =SUM(C36:C39) -> 1619 | D40: =SUM(D36:D39) -> 2113 | E40: =SUM(E36:E39) -> 2404 | F40: =SUM(F36:F39) -> 2549 | G40: =F40+170 -> 2719 | H40: =SUM(H36:H39) -> 2877 | I40: =SUM(I36:I39) -> 3050 | J40: =SUM(J36:J39) -> 3239 | K40: =SUM(K36:K39) -> 3446 | L40: =SUM(L36:L39) -> 3671 | M40: =(L40/G40)^(1/5)-1 -> 0.061879008
B42: Systemwide Sales
B43: Club Pilates | E43: =E50*E36/1000 -> 790.49256 | F43: 958 | G43: =G50*G36/1000 -> 1085.414 | H43: =H50*H36/1000 -> 1229.7741 | I43: =I50*I36/1000 -> 1393.1595 | J43: =J50*J36/1000 -> 1578.7193 | K43: =K50*K36/1000 -> 1788.9666 | L43: =L50*L36/1000 -> 2026.6132 | M43: =(L43/G43)^(1/5)-1 -> 0.13301352
B44: StretchLab | E44: =E51*E37/1000 -> 243.15988 | F44: 260 | G44: =G51*G37/1000 -> 286.04915 | H44: =H51*H37/1000 -> 300.30246 | I44: =I51*I37/1000 -> 315.53875 | J44: =J51*J37/1000 -> 331.26654 | K44: =K51*K37/1000 -> 347.97732 | L44: =L51*L37/1000 -> 365.17958 | M44: =(L44/G44)^(1/5)-1 -> 0.050057705
B45: Pure Barre | E45: =E52*E38/1000 -> 224.1881 | F45: 228 | G45: =G52*G38/1000 -> 225.8147 | H45: =H52*H38/1000 -> 223.62939 | I45: =I52*I38/1000 -> 221.44409 | J45: =J52*J38/1000 -> 219.25879 | K45: =K52*K38/1000 -> 217.07348 | L45: =L52*L38/1000 -> 214.88818 | M45: =(L45/G45)^(1/5)-1 -> -0.0098703534
B46: YogaSix | E46: =E53*E39/1000 -> 83.592686 | F46: 90 | G46: =G53*G39/1000 -> 91.391753 | H46: =H53*H39/1000 -> 92.783505 | I46: =I53*I39/1000 -> 94.175258 | J46: =J53*J39/1000 -> 95.56701 | K46: =K53*K39/1000 -> 96.958763 | L46: =L53*L39/1000 -> 98.350515 | M46: =(L46/G46)^(1/5)-1 -> 0.014784738
B47: Total | E47: =SUM(E43:E46) -> 1341.4332 | F47: =SUM(F43:F46) -> 1536 | G47: =SUM(G43:G46) -> 1688.6696 | H47: =SUM(H43:H46) -> 1846.4894 | I47: =SUM(I43:I46) -> 2024.3176 | J47: =SUM(J43:J46) -> 2224.8117 | K47: =SUM(K43:K46) -> 2450.9762 | L47: =SUM(L43:L46) -> 2705.0315 | M47: =(L47/G47)^(1/5)-1 -> 0.098817401
B49: Implied Blended AUV ($000s)
B50: Club Pilates | E50: =F50/(1+F69) -> 712.79762 | F50: =F43/F36*1000 -> 798.33333 | G50: =(1+G69)*F50 -> 822.28333 | H50: =(1+H69)*G50 -> 846.95183 | I50: =(1+I69)*H50 -> 872.36039 | J50: =(1+J69)*I50 -> 898.5312 | K50: =(1+K69)*J50 -> 925.48714 | L50: =(1+L69)*K50 -> 953.25175 | M50: =(L50/G50)^(1/5)-1 -> 0.03
B51: StretchLab | E51: =F51/(1+F70) -> 517.36146 | F51: =F44/F37*1000 -> 491.49338 | G51: =(1+G70)*F51 -> 491.49338 | H51: =(1+H70)*G51 -> 491.49338 | I51: =(1+I70)*H51 -> 491.49338 | J51: =(1+J70)*I51 -> 491.49338 | K51: =(1+K70)*J51 -> 491.49338 | L51: =(1+L70)*K51 -> 491.49338 | M51: =(L51/G51)^(1/5)-1 -> 0
B52: Pure Barre | E52: =F52/(1+F71) -> 353.60898 | F52: =F45/F38*1000 -> 364.21725 | G52: =(1+G71)*F52 -> 364.21725 | H52: =(1+H71)*G52 -> 364.21725 | I52: =(1+I71)*H52 -> 364.21725 | J52: =(1+J71)*I52 -> 364.21725 | K52: =(1+K71)*J52 -> 364.21725 | L52: =(1+L71)*K52 -> 364.21725 | M52: =(L52/G52)^(1/5)-1 -> 0
B53: YogaSix | E53: =F53/(1+F72) -> 437.65804 | F53: =F46/F39*1000 -> 463.91753 | G53: =(1+G72)*F53 -> 463.91753 | H53: =(1+H72)*G53 -> 463.91753 | I53: =(1+I72)*H53 -> 463.91753 | J53: =(1+J72)*I53 -> 463.91753 | K53: =(1+K72)*J53 -> 463.91753 | L53: =(1+L72)*K53 -> 463.91753 | M53: =(L53/G53)^(1/5)-1 -> 0
B54: Total | E54: =E47/E40*1000 -> 558.00051 | F54: =F47/F40*1000 -> 602.58925 | G54: =G47/G40*1000 -> 621.06274 | H54: =H47/H40*1000 -> 641.81071 | I54: =I47/I40*1000 -> 663.7107 | J54: =J47/J40*1000 -> 686.88226 | K54: =K47/K40*1000 -> 711.25252 | L54: =L47/L40*1000 -> 736.86502 | M54: =(L54/G54)^(1/5)-1 -> 0.034785878
B56: Core EBITDA Contribution
B57: Club Pilates | F57: 102 | G57: =G43*G90 -> 115.566 | H57: =H43*H90 -> 130.93628 | I57: =I43*I90 -> 148.33223 | J57: =J43*J90 -> 168.08911 | K57: =K43*K90 -> 190.47453 | L57: =L43*L90 -> 215.77719 | M57: =(L57/G57)^(1/5)-1 -> 0.13301352
B58: StretchLab | F58: 29 | G58: =G44*G91 -> 31.905482 | H58: =H44*H91 -> 33.495274 | I58: =I44*I91 -> 35.194707 | J58: =J44*J91 -> 36.94896 | K58: =K44*K91 -> 38.812854 | L58: =L44*L91 -> 40.731569 | M58: =(L58/G58)^(1/5)-1 -> 0.050057705
B59: Pure Barre | F59: 21 | G59: =G45*G92 -> 20.798722 | H59: =H45*H92 -> 20.597444 | I59: =I45*I92 -> 20.396166 | J59: =J45*J92 -> 20.194888 | K59: =K45*K92 -> 19.99361 | L59: =L45*L92 -> 19.792332 | M59: =(L59/G59)^(1/5)-1 -> -0.0098703534
B60: YogaSix | F60: 8 | G60: =G46*G93 -> 8.1237113 | H60: =H46*H93 -> 8.2474227 | I60: =I46*I93 -> 8.371134 | J60: =J46*J93 -> 8.4948454 | K60: =K46*K93 -> 8.6185567 | L60: =L46*L93 -> 8.742268 | M60: =(L60/G60)^(1/5)-1 -> 0.014784738
B61: Total | F61: =SUM(F57:F60) -> 160 | G61: =SUM(G57:G60) -> 176.39392 | H61: =SUM(H57:H60) -> 193.27642 | I61: =SUM(I57:I60) -> 212.29423 | J61: =SUM(J57:J60) -> 233.72781 | K61: =SUM(K57:K60) -> 257.89955 | L61: =SUM(L57:L60) -> 285.04336 | M61: =(L61/G61)^(1/5)-1 -> 0.10074182
B63: Core Brand EBITDA | F63: =F61 -> 160 | G63: =G61 -> 176.39392 | H63: =H61 -> 193.27642 | I63: =I61 -> 212.29423 | J63: =J61 -> 233.72781 | K63: =K61 -> 257.89955 | L63: =L61 -> 285.04336
B64: (+) Other Brands and Int'l EBITDA | F64: =5+9 -> 14 | G64: =(G61/F61)*F64 -> 15.434468 | H64: =(H61/G61)*G64 -> 16.911687 | I64: =(I61/H61)*H64 -> 18.575745 | J64: =(J61/I61)*I64 -> 20.451183 | K64: =(K61/J61)*J64 -> 22.56621 | L64: =(L61/K61)*K64 -> 24.941294
B65: (-) Overhead & Other Expense | F65: =F66-SUM(F63:F64) -> -84 | G65: =G66-SUM(G63:G64) -> -81.828383 | H65: =G65-10 -> -91.828383 | I65: =H65-10 -> -101.82838 | J65: =I65-10 -> -111.82838 | K65: =J65-10 -> -121.82838 | L65: =K65-10 -> -131.82838
B66: Adj. EBITDA | F66: 90 | G66: 110 | H66: =SUM(H63:H65) -> 118.35972 | I66: =SUM(I63:I65) -> 129.0416 | J66: =SUM(J63:J65) -> 142.35061 | K66: =SUM(K63:K65) -> 158.63738 | L66: =SUM(L63:L65) -> 178.15627 | M66: =(L66/G66)^(1/5)-1 -> 0.10123926
B68: Implied Blended SSS
B69: Club Pilates | F69: 0.12 | G69: 0.03 | H69: 0.03 | I69: 0.03 | J69: 0.03 | K69: 0.03 | L69: 0.03
B70: StretchLab | F70: -0.05 | G70: 0 | H70: 0 | I70: 0 | J70: 0 | K70: 0 | L70: 0
B71: Pure Barre | F71: 0.03 | G71: 0 | H71: 0 | I71: 0 | J71: 0 | K71: 0 | L71: 0
B72: YogaSix | F72: 0.06 | G72: 0 | H72: 0 | I72: 0 | J72: 0 | K72: 0 | L72: 0
B73: Total | F73: 0.1 | G73: =G54/F54-1 -> 0.030656857 | H73: =H54/G54-1 -> 0.033407202 | I73: =I54/H54-1 -> 0.034122194 | J73: =J54/I54-1 -> 0.034912143 | K73: =K54/J54-1 -> 0.035479528 | L73: =L54/K54-1 -> 0.036010417
B75: Studios - # Change
B76: Club Pilates | D76: =D36-C36 -> 227 | E76: =E36-D36 -> 156 | F76: =F36-E36 -> 91 | G76: =G36-F36 -> 120 | H76: =H36-G36 -> 132 | I76: =I36-H36 -> 145 | J76: =J36-I36 -> 160 | K76: =K36-J36 -> 176 | L76: =L36-K36 -> 193 | M76: =(L76/G76)^(1/5)-1 -> 0.099702501
B77: StretchLab | D77: =D37-C37 -> 165 | E77: =E37-D37 -> 112 | F77: =F37-E37 -> 59 | G77: =G37-F37 -> 53 | H77: =H37-G37 -> 29 | I77: =I37-H37 -> 31 | J77: =J37-I37 -> 32 | K77: =K37-J37 -> 34 | L77: =L37-K37 -> 35 | M77: =(L77/G77)^(1/5)-1 -> -0.079638518
B78: Pure Barre | D78: =D38-C38 -> 33 | E78: =E38-D38 -> 10 | F78: =F38-E38 -> -8 | G78: =G38-F38 -> -6 | H78: =H38-G38 -> -6 | I78: =I38-H38 -> -6 | J78: =J38-I38 -> -6 | K78: =K38-J38 -> -6 | L78: =L38-K38 -> -6 | M78: =(L78/G78)^(1/5)-1 -> 0
B79: YogaSix | D79: =D39-C39 -> 69 | E79: =E39-D39 -> 13 | F79: =F39-E39 -> 3 | G79: =G39-F39 -> 3 | H79: =H39-G39 -> 3 | I79: =I39-H39 -> 3 | J79: =J39-I39 -> 3 | K79: =K39-J39 -> 3 | L79: =L39-K39 -> 3 | M79: =(L79/G79)^(1/5)-1 -> 0
B80: Total | D80: =D40-C40 -> 494 | E80: =E40-D40 -> 291 | F80: =F40-E40 -> 145 | G80: =G40-F40 -> 170 | H80: =H40-G40 -> 158 | I80: =I40-H40 -> 173 | J80: =J40-I40 -> 189 | K80: =K40-J40 -> 207 | L80: =L40-K40 -> 225 | M80: =(L80/G80)^(1/5)-1 -> 0.057661557
B82: Studios - % Change
B83: Club Pilates | D83: =D36/C36-1 -> 0.31267218 | E83: =E36/D36-1 -> 0.1636936 | F83: =F36/E36-1 -> 0.082055906 | G83: 0.1 | H83: 0.1 | I83: 0.1 | J83: 0.1 | K83: 0.1 | L83: 0.1
B84: StretchLab | D84: =D37/C37-1 -> 0.85492228 | E84: =E37/D37-1 -> 0.31284916 | F84: =F37/E37-1 -> 0.12553191 | G84: 0.1 | H84: 0.05 | I84: 0.05 | J84: 0.05 | K84: 0.05 | L84: 0.05
B85: Pure Barre | D85: =D38/C38-1 -> 0.055837563 | E85: =E38/D38-1 -> 0.016025641 | F85: =F38/E38-1 -> -0.012618297 | G85: -0.01 | H85: -0.01 | I85: -0.01 | J85: -0.01 | K85: -0.01 | L85: -0.01
B86: YogaSix | D86: =D39/C39-1 -> 0.63302752 | E86: =E39/D39-1 -> 0.073033708 | F86: =F39/E39-1 -> 0.015706806 | G86: =G39/F39-1 -> 0.015463918 | H86: =G86 -> 0.015463918 | I86: =H86 -> 0.015463918 | J86: =I86 -> 0.015463918 | K86: =J86 -> 0.015463918 | L86: =K86 -> 0.015463918
B87: Total | D87: =D40/C40-1 -> 0.30512662 | E87: =E40/D40-1 -> 0.13771888 | F87: =F40/E40-1 -> 0.06031614 | G87: =G40/F40-1 -> 0.066692821 | H87: =H40/G40-1 -> 0.058109599 | I87: =I40/H40-1 -> 0.060132082 | J87: =J40/I40-1 -> 0.061967213 | K87: =K40/J40-1 -> 0.063908614 | L87: =L40/K40-1 -> 0.065293093
B89: EBITDA Contribution %
B90: Club Pilates | F90: =F57/F43 -> 0.10647182 | G90: =F90 -> 0.10647182 | H90: =G90 -> 0.10647182 | I90: =H90 -> 0.10647182 | J90: =I90 -> 0.10647182 | K90: =J90 -> 0.10647182 | L90: =K90 -> 0.10647182
B91: StretchLab | F91: =F58/F44 -> 0.11153846 | G91: =F91 -> 0.11153846 | H91: =G91 -> 0.11153846 | I91: =H91 -> 0.11153846 | J91: =I91 -> 0.11153846 | K91: =J91 -> 0.11153846 | L91: =K91 -> 0.11153846
B92: Pure Barre | F92: =F59/F45 -> 0.092105263 | G92: =F92 -> 0.092105263 | H92: =G92 -> 0.092105263 | I92: =H92 -> 0.092105263 | J92: =I92 -> 0.092105263 | K92: =J92 -> 0.092105263 | L92: =K92 -> 0.092105263
B93: YogaSix | F93: =F60/F46 -> 0.088888889 | G93: =F93 -> 0.088888889 | H93: =G93 -> 0.088888889 | I93: =H93 -> 0.088888889 | J93: =I93 -> 0.088888889 | K93: =J93 -> 0.088888889 | L93: =K93 -> 0.088888889
B94: Total | F94: =F61/F47 -> 0.10416667 | G94: =G61/G47 -> 0.10445733 | H94: =H61/H47 -> 0.10467237 | I94: =I61/I47 -> 0.104872 | J94: =J61/J47 -> 0.1050551 | K94: =K61/K47 -> 0.1052232 | L94: =L61/L47 -> 0.10537525
M96: Reference: Unit Economics
M97: Brand | N97: Est. Four-Wall Margin | O97: Unit Investment (Est.) | P97: Sales ÷ Investment Ratio
M98: Club Pilates | N98: 35–40% | O98: $250K–$300K | P98: ~3.7x–4.1x
M99: StretchLab | N99: 25–30% | O99: $160K–$250K | P99: ~2.2x–3.4x
M100: Pure Barre | N100: 25–30% | O100: $180K–$300K | P100: ~1.3x–2.2x
M101: YogaSix | N101: 25–30% | O101: $225K–$350K | P101: ~1.3x–2.1x
M102: All Other Brands | N102: <25% | O102: $200K–$400K | P102: ~1.2x–2.3x

Sheet ST
A2: =Summary!C8 -> 46113 | B2: Current Capitalization
B3: Current Share Price | F3: =32.45 -> 32.45
B4: Diluted Shares Outstanding | F4: 145.7
B5: Market Cap | F5: =F3*F4 -> 4727.965
B6: (+) Debt | F6: =3203.2 -> 3203.2
B7: (-) Cash | F7: -791.3
B8: TEV | F8: =SUM(F5:F7) -> 7139.865
B9: 2025E EV / EBITDA | F9: =F8/E42 -> 8.3720656
B10: 2026E EV / EBITDA | F10: =F8/F42 -> 8.0061281
A12: =Summary!G8 -> 47848 | B12: Exit
B13: 2030E EBITDA | F13: =J42 -> 1442.0024
B14: EV / EBITDA | F14: =Summary!H8 -> 10
B15: TEV | F15: =F13*F14 -> 14420.024
B16: (-) Current Net Debt | F16: =-F6 -> -3203.2
B17: (+) Cumulative Levered FCF | F17: =F33 -> 3601.8399
B18: Market Cap | F18: =SUM(F15:F17) -> 14818.664
B19: Current Shares Outstanding | F19: =F4 -> 145.7
B20: Implied Share Price | F20: =F18/F19 -> 101.70669
B22: Remaining Upside
B23: Gross Upside | F23: =F20/F3-1 -> 2.1342584
B24: MOIC | F24: =F20/F3 -> 3.1342584
A25: =(A12-A2)/365 -> 4.7534247 | B25: IRR | F25: =F24^(1/A25)-1 -> 0.27166928
B27: Memo: Cash Flows
B28: Cumulative EBITDA | F28: =SUM(F42:J42) -> 5626.2186
B29: Cumulative D&A | F29: =SUM(F46:J46) -> 4077.8812
A30: 200 | B30: Cumulative Interest Expense | F30: =A30*5 -> 1000
B31: Cumulative Capex | F31: =SUM(F49:J49) -> 714.71121
A32: 0.2 | B32: Cumulative Taxes | F32: =(F28-F29)*A32 -> 309.66747
B33: Cumulative Levered FCF | F33: =F28-SUM(F30:F32) -> 3601.8399
K35: '25E - '30E
C36: 2023A | D36: 2024A | E36: 2025E | F36: 2026E | G36: 2027E | H36: 2028E | I36: 2029E | J36: 2030E | K36: CAGR
B37: Revenue
B38: Total | C38: 4054.1 | D38: 3932.8 | E38: 3694.28 | F38: 3810.36 | G38: 4007.98 | H38: =G38*(1+H39) -> 4609.177 | I38: =H38*(1+I39) -> 5300.5535 | J38: =I38*(1+J39) -> 6095.6366 | K38: =(J38/E38)^(1/5)-1 -> 0.105345
B39: % Growth | D39: =D38/C38-1 -> -0.029920328 | E39: =E38/D38-1 -> -0.060648902 | F39: =F38/E38-1 -> 0.031421549 | G39: =G38/F38-1 -> 0.051863866 | H39: 0.15 | I39: 0.15 | J39: 0.15
B41: EBITDA
B42: Total | C42: 878.8 | D42: 764.4 | E42: 852.82 | F42: 891.8 | G42: 948.14 | H42: =G42*(1+H43) -> 1090.361 | I42: =H42*(1+I43) -> 1253.9152 | J42: =I42*(1+J43) -> 1442.0024 | K42: =(J42/E42)^(1/5)-1 -> 0.11076381
B43: % Growth | D43: =D42/C42-1 -> -0.13017751 | E43: =E42/D42-1 -> 0.11567242 | F43: =F42/E42-1 -> 0.045707183 | G43: =G42/F42-1 -> 0.0631756 | H43: 0.15 | I43: 0.15 | J43: 0.15
B44: % Margin | C44: =C42/C38 -> 0.21676821 | D44: =D42/D38 -> 0.19436534 | E44: =E42/E38 -> 0.23084877 | F44: =F42/F38 -> 0.23404613 | G44: =G42/G38 -> 0.23656306 | H44: =H42/H38 -> 0.23656306 | I44: =I42/I38 -> 0.23656306 | J44: =J42/J38 -> 0.23656306
B46: D&A | C46: 300.8 | D46: 307.7 | E46: 600 | F46: =E46*1.12 -> 672 | G46: =F46*1.015 -> 682.08 | H46: =H47*H38 -> 784.392 | I46: =I47*I38 -> 902.0508 | J46: =J47*J38 -> 1037.3584 | K46: =(J46/E46)^(1/5)-1 -> 0.11572077
B47: % Revenue | C47: =C46/C38 -> 0.074196492 | D47: =D46/D38 -> 0.078239422 | E47: =E46/E38 -> 0.16241324 | F47: =F46/F38 -> 0.17636129 | G47: =G46/G38 -> 0.17018049 | H47: =G47 -> 0.17018049 | I47: =H47 -> 0.17018049 | J47: =I47 -> 0.17018049
B49: Capex | C49: 184.6 | D49: 158.6 | E49: =D49*1+E50 -> 158.642 | F49: =F50*F38 -> 114.3108 | G49: =G50*G38 -> 120.2394 | H49: =H50*H38 -> 138.27531 | I49: =I50*I38 -> 159.01661 | J49: =J50*J38 -> 182.8691 | K49: =(J49/E49)^(1/5)-1 -> 0.028831918
B50: % Revenue | C50: =C49/C38 -> 0.045534151 | D50: =D49/D38 -> 0.040327502 | E50: =0.042 -> 0.042 | F50: 0.03 | G50: 0.03 | H50: 0.03 | I50: 0.03 | J50: 0.03

Sheet RDDT
B1: (USD $M, FYE December) | C1: FY2022A | D1: FY2023A | E1: FY2024A | F1: FY2025A | G1: FY2026E | H1: FY2027E | I1: FY2028E | J1: FY2029E | K1: FY2030E | L1: '26E-'30E
B2: Revenue
B3: Advertising | C3: 580 | D3: 758 | E3: 1119 | F3: 1834 | G3: 2580 | H3: 3354 | I3: 4191 | J3: 5113 | K3: 6084
B4: Data Licensing | C4: 0 | D4: 0 | E4: 138 | F4: 313 | G4: 470 | H4: 610 | I4: 815 | J4: 1050 | K4: 1310
B5: Other Revenue | C5: 87 | D5: 46 | E5: 43 | F5: 56 | G5: 92 | H5: 128 | I5: 165 | J5: 197 | K5: 238
B6: Consolidated Total | C6: =SUM(C3:C5) -> 667 | D6: =SUM(D3:D5) -> 804 | E6: =SUM(E3:E5) -> 1300 | F6: =SUM(F3:F5) -> 2203 | G6: =SUM(G3:G5) -> 3142 | H6: =SUM(H3:H5) -> 4092 | I6: =SUM(I3:I5) -> 5171 | J6: =SUM(J3:J5) -> 6360 | K6: =SUM(K3:K5) -> 7632 | L6: =(K6/G6)^(1/4)-1 -> 0.24841232
B8: Revenue - YoY Growth %
B9: Advertising | D9: =IFERROR(D3/C3-1,"-") -> 0.30689655 | E9: =IFERROR(E3/D3-1,"-") -> 0.4762533 | F9: =IFERROR(F3/E3-1,"-") -> 0.63896336 | G9: =IFERROR(G3/F3-1,"-") -> 0.40676118 | H9: =IFERROR(H3/G3-1,"-") -> 0.3 | I9: =IFERROR(I3/H3-1,"-") -> 0.24955277 | J9: =IFERROR(J3/I3-1,"-") -> 0.21999523 | K9: =IFERROR(K3/J3-1,"-") -> 0.18990808
B10: Data Licensing | D10: =IFERROR(D4/C4-1,"-") -> - | E10: =IFERROR(E4/D4-1,"-") -> - | F10: =IFERROR(F4/E4-1,"-") -> 1.2681159 | G10: =IFERROR(G4/F4-1,"-") -> 0.50159744 | H10: =IFERROR(H4/G4-1,"-") -> 0.29787234 | I10: =IFERROR(I4/H4-1,"-") -> 0.33606557 | J10: =IFERROR(J4/I4-1,"-") -> 0.28834356 | K10: =IFERROR(K4/J4-1,"-") -> 0.24761905
B11: Other Revenue | D11: =IFERROR(D5/C5-1,"-") -> -0.47126437 | E11: =IFERROR(E5/D5-1,"-") -> -0.065217391 | F11: =IFERROR(F5/E5-1,"-") -> 0.30232558 | G11: =IFERROR(G5/F5-1,"-") -> 0.64285714 | H11: =IFERROR(H5/G5-1,"-") -> 0.39130435 | I11: =IFERROR(I5/H5-1,"-") -> 0.2890625 | J11: =IFERROR(J5/I5-1,"-") -> 0.19393939 | K11: =IFERROR(K5/J5-1,"-") -> 0.20812183
B12: Consolidated Total | D12: =IFERROR(D6/C6-1,"-") -> 0.2053973 | E12: =IFERROR(E6/D6-1,"-") -> 0.61691542 | F12: =IFERROR(F6/E6-1,"-") -> 0.69461538 | G12: =IFERROR(G6/F6-1,"-") -> 0.42623695 | H12: =IFERROR(H6/G6-1,"-") -> 0.30235519 | I12: =IFERROR(I6/H6-1,"-") -> 0.26368524 | J12: =IFERROR(J6/I6-1,"-") -> 0.22993618 | K12: =IFERROR(K6/J6-1,"-") -> 0.2
B14: Revenue Mix %
B15: Advertising | C15: =IFERROR(C3/C6,"-") -> 0.86956522 | D15: =IFERROR(D3/D6,"-") -> 0.94278607 | E15: =IFERROR(E3/E6,"-") -> 0.86076923 | F15: =IFERROR(F3/F6,"-") -> 0.83250113 | G15: =IFERROR(G3/G6,"-") -> 0.82113304 | H15: =IFERROR(H3/H6,"-") -> 0.81964809 | I15: =IFERROR(I3/I6,"-") -> 0.81048153 | J15: =IFERROR(J3/J6,"-") -> 0.80393082 | K15: =IFERROR(K3/K6,"-") -> 0.79716981
B16: Data Licensing | C16: =IFERROR(C4/C6,"-") -> 0 | D16: =IFERROR(D4/D6,"-") -> 0 | E16: =IFERROR(E4/E6,"-") -> 0.10615385 | F16: =IFERROR(F4/F6,"-") -> 0.14207898 | G16: =IFERROR(G4/G6,"-") -> 0.14958625 | H16: =IFERROR(H4/H6,"-") -> 0.14907136 | I16: =IFERROR(I4/I6,"-") -> 0.15760975 | J16: =IFERROR(J4/J6,"-") -> 0.16509434 | K16: =IFERROR(K4/K6,"-") -> 0.1716457
B17: Other Revenue | C17: =IFERROR(C5/C6,"-") -> 0.13043478 | D17: =IFERROR(D5/D6,"-") -> 0.05721393 | E17: =IFERROR(E5/E6,"-") -> 0.033076923 | F17: =IFERROR(F5/F6,"-") -> 0.025419882 | G17: =IFERROR(G5/G6,"-") -> 0.029280713 | H17: =IFERROR(H5/H6,"-") -> 0.031280547 | I17: =IFERROR(I5/I6,"-") -> 0.031908722 | J17: =IFERROR(J5/J6,"-") -> 0.030974843 | K17: =IFERROR(K5/K6,"-") -> 0.031184486
B18: Total | C18: =IFERROR(C6/C6,"-") -> 1 | D18: =IFERROR(D6/D6,"-") -> 1 | E18: =IFERROR(E6/E6,"-") -> 1 | F18: =IFERROR(F6/F6,"-") -> 1 | G18: =IFERROR(G6/G6,"-") -> 1 | H18: =IFERROR(H6/H6,"-") -> 1 | I18: =IFERROR(I6/I6,"-") -> 1 | J18: =IFERROR(J6/J6,"-") -> 1 | K18: =IFERROR(K6/K6,"-") -> 1
B20: Key Operating Metrics
B21: DAUq (M) | D21: 52 | E21: 82 | F21: 101 | G21: 118 | H21: 135 | I21: 152 | J21: 168 | K21: 182
B22: DAUq YoY Growth | E22: =IFERROR(E21/D21-1,"-") -> 0.57692308 | F22: =IFERROR(F21/E21-1,"-") -> 0.23170732 | G22: =IFERROR(G21/F21-1,"-") -> 0.16831683 | H22: =IFERROR(H21/G21-1,"-") -> 0.1440678 | I22: =IFERROR(I21/H21-1,"-") -> 0.12592593 | J22: =IFERROR(J21/I21-1,"-") -> 0.10526316 | K22: =IFERROR(K21/J21-1,"-") -> 0.083333333
B23: Global ARPU ($) | D23: =IFERROR(D6/D21,"-") -> 15.461538 | E23: =IFERROR(E6/E21,"-") -> 15.853659 | F23: =IFERROR(F6/F21,"-") -> 21.811881 | G23: =IFERROR(G6/G21,"-") -> 26.627119 | H23: =IFERROR(H6/H21,"-") -> 30.311111 | I23: =IFERROR(I6/I21,"-") -> 34.019737 | J23: =IFERROR(J6/J21,"-") -> 37.857143 | K23: =IFERROR(K6/K21,"-") -> 41.934066
B24: ARPU YoY Growth | E24: =IFERROR(E23/D23-1,"-") -> 0.025361 | F24: =IFERROR(F23/E23-1,"-") -> 0.37582635 | G24: =IFERROR(G23/F23-1,"-") -> 0.22076213 | H24: =IFERROR(H23/G23-1,"-") -> 0.1383549 | I24: =IFERROR(I23/H23-1,"-") -> 0.12235202 | J24: =IFERROR(J23/I23-1,"-") -> 0.1127994 | K24: =IFERROR(K23/J23-1,"-") -> 0.10769231
B26: Cost Structure
B27: Cost of Revenue | C27: 119 | D27: 131 | E27: 153 | F27: 194 | G27: 275 | H27: 350 | I27: 430 | J27: 510 | K27: 595
B28: Gross Profit | C28: =C6-C27 -> 548 | D28: =D6-D27 -> 673 | E28: =E6-E27 -> 1147 | F28: =F6-F27 -> 2009 | G28: =G6-G27 -> 2867 | H28: =H6-H27 -> 3742 | I28: =I6-I27 -> 4741 | J28: =J6-J27 -> 5850 | K28: =K6-K27 -> 7037
B29: Gross Margin | C29: =IFERROR(C28/C6,"-") -> 0.82158921 | D29: =IFERROR(D28/D6,"-") -> 0.83706468 | E29: =IFERROR(E28/E6,"-") -> 0.88230769 | F29: =IFERROR(F28/F6,"-") -> 0.91193827 | G29: =IFERROR(G28/G6,"-") -> 0.91247613 | H29: =IFERROR(H28/H6,"-") -> 0.91446725 | I29: =IFERROR(I28/I6,"-") -> 0.91684394 | J29: =IFERROR(J28/J6,"-") -> 0.91981132 | K29: =IFERROR(K28/K6,"-") -> 0.92203878
B31: Operating Expenses
B32: R&D | C32: 477 | D32: 468 | E32: 1155 | F32: 981 | G32: 1080 | H32: 1230 | I32: 1400 | J32: 1570 | K32: 1720
B33: % of Revenue | C33: =IFERROR(C32/C6,"-") -> 0.71514243 | D33: =IFERROR(D32/D6,"-") -> 0.58208955 | E33: =IFERROR(E32/E6,"-") -> 0.88846154 | F33: =IFERROR(F32/F6,"-") -> 0.44530186 | G33: =IFERROR(G32/G6,"-") -> 0.34373011 | H33: =IFERROR(H32/H6,"-") -> 0.30058651 | I33: =IFERROR(I32/I6,"-") -> 0.27074067 | J33: =IFERROR(J32/J6,"-") -> 0.24685535 | K33: =IFERROR(K32/K6,"-") -> 0.22536688
B34: S&M | C34: 86 | D34: 100 | E34: 153 | F34: 178 | G34: 260 | H34: 320 | I34: 380 | J34: 435 | K34: 490
B35: % of Revenue | C35: =IFERROR(C34/C6,"-") -> 0.12893553 | D35: =IFERROR(D34/D6,"-") -> 0.12437811 | E35: =IFERROR(E34/E6,"-") -> 0.11769231 | F35: =IFERROR(F34/F6,"-") -> 0.080798911 | G35: =IFERROR(G34/G6,"-") -> 0.082749841 | H35: =IFERROR(H34/H6,"-") -> 0.078201369 | I35: =IFERROR(I34/I6,"-") -> 0.073486753 | J35: =IFERROR(J34/J6,"-") -> 0.068396226 | K35: =IFERROR(K34/K6,"-") -> 0.064203354
B36: G&A | C36: 168 | D36: 198 | E36: 525 | F36: 263 | G36: 290 | H36: 330 | I36: 360 | J36: 390 | K36: 420
B37: % of Revenue | C37: =IFERROR(C36/C6,"-") -> 0.25187406 | D37: =IFERROR(D36/D6,"-") -> 0.24626866 | E37: =IFERROR(E36/E6,"-") -> 0.40384615 | F37: =IFERROR(F36/F6,"-") -> 0.11938266 | G37: =IFERROR(G36/G6,"-") -> 0.092297899 | H37: =IFERROR(H36/H6,"-") -> 0.080645161 | I37: =IFERROR(I36/I6,"-") -> 0.069619029 | J37: =IFERROR(J36/J6,"-") -> 0.061320755 | K37: =IFERROR(K36/K6,"-") -> 0.055031447
B38: Total OpEx | C38: =C32+C34+C36 -> 731 | D38: =D32+D34+D36 -> 766 | E38: =E32+E34+E36 -> 1833 | F38: =F32+F34+F36 -> 1422 | G38: =G32+G34+G36 -> 1630 | H38: =H32+H34+H36 -> 1880 | I38: =I32+I34+I36 -> 2140 | J38: =J32+J34+J36 -> 2395 | K38: =K32+K34+K36 -> 2630
B40: EBITDA | C40: =C28-C38 -> -183 | D40: =D28-D38 -> -93 | E40: =E28-E38 -> -686 | F40: =F28-F38 -> 587 | G40: =G28-G38 -> 1237 | H40: =H28-H38 -> 1862 | I40: =I28-I38 -> 2601 | J40: =J28-J38 -> 3455 | K40: =K28-K38 -> 4407 | L40: =(K40/G40)^(1/4)-1 -> 0.37386272
B41: EBITDA Margin | C41: =IFERROR(C40/C6,"-") -> -0.27436282 | D41: =IFERROR(D40/D6,"-") -> -0.11567164 | E41: =IFERROR(E40/E6,"-") -> -0.52769231 | F41: =IFERROR(F40/F6,"-") -> 0.26645483 | G41: =IFERROR(G40/G6,"-") -> 0.39369828 | H41: =IFERROR(H40/H6,"-") -> 0.45503421 | I41: =IFERROR(I40/I6,"-") -> 0.50299749 | J41: =IFERROR(J40/J6,"-") -> 0.54323899 | K41: =IFERROR(K40/K6,"-") -> 0.57743711
B42: EBITDA YoY Growth | D42: =IFERROR(D40/C40-1,"-") -> -0.49180328 | E42: =IFERROR(E40/D40-1,"-") -> 6.3763441 | F42: =IFERROR(F40/E40-1,"-") -> -1.8556851 | G42: =IFERROR(G40/F40-1,"-") -> 1.1073254 | H42: =IFERROR(H40/G40-1,"-") -> 0.50525465 | I42: =IFERROR(I40/H40-1,"-") -> 0.39688507 | J42: =IFERROR(J40/I40-1,"-") -> 0.32833526 | K42: =IFERROR(K40/J40-1,"-") -> 0.27554269
B44: D&A | C44: 11 | D44: 14 | E44: 16 | F44: 16 | G44: 18 | H44: 20 | I44: 23 | J44: 26 | K44: 30
B45: % of Revenue | C45: =IFERROR(C44/C6,"-") -> 0.016491754 | D45: =IFERROR(D44/D6,"-") -> 0.017412935 | E45: =IFERROR(E44/E6,"-") -> 0.012307692 | F45: =IFERROR(F44/F6,"-") -> 0.0072628234 | G45: =IFERROR(G44/G6,"-") -> 0.0057288351 | H45: =IFERROR(H44/H6,"-") -> 0.0048875855 | I45: =IFERROR(I44/I6,"-") -> 0.0044478824 | J45: =IFERROR(J44/J6,"-") -> 0.0040880503 | K45: =IFERROR(K44/K6,"-") -> 0.0039308176
B47: Capital Expenditure | C47: 8 | D47: 10 | E47: 6 | F47: 7 | G47: 10 | H47: 12 | I47: 15 | J47: 19 | K47: 23
B48: % of Revenue | C48: =IFERROR(C47/C6,"-") -> 0.011994003 | D48: =IFERROR(D47/D6,"-") -> 0.012437811 | E48: =IFERROR(E47/E6,"-") -> 0.0046153846 | F48: =IFERROR(F47/F6,"-") -> 0.0031774852 | G48: =IFERROR(G47/G6,"-") -> 0.0031826862 | H48: =IFERROR(H47/H6,"-") -> 0.0029325513 | I48: =IFERROR(I47/I6,"-") -> 0.0029007929 | J48: =IFERROR(J47/J6,"-") -> 0.0029874214 | K48: =IFERROR(K47/K6,"-") -> 0.0030136268
B50: Stock-Based Compensation | C50: 87 | D50: 527 | E50: 1034 | F50: 620 | G50: 470 | H50: 440 | I50: 420 | J50: 400 | K50: 385
B51: % of Revenue | C51: =IFERROR(C50/C6,"-") -> 0.13043478 | D51: =IFERROR(D50/D6,"-") -> 0.65547264 | E51: =IFERROR(E50/E6,"-") -> 0.79538462 | F51: =IFERROR(F50/F6,"-") -> 0.28143441 | G51: =IFERROR(G50/G6,"-") -> 0.14958625 | H51: =IFERROR(H50/H6,"-") -> 0.10752688 | I51: =IFERROR(I50/I6,"-") -> 0.081222201 | J51: =IFERROR(J50/J6,"-") -> 0.062893082 | K51: =IFERROR(K50/K6,"-") -> 0.050445493
B53: Free Cash Flow | C53: -85 | D53: -85 | E53: 216 | F53: 684 | G53: =G40*(1-$A$72)-G47 -> 1041.45 | H53: =H40*(1-$A$72)-H47 -> 1570.7 | I53: =I40*(1-$A$72)-I47 -> 2195.85 | J53: =J40*(1-$A$72)-J47 -> 2917.75 | K53: =K40*(1-$A$72)-K47 -> 3722.95
B54: FCF Margin | C54: =IFERROR(C53/C6,"-") -> -0.12743628 | D54: =IFERROR(D53/D6,"-") -> -0.10572139 | E54: =IFERROR(E53/E6,"-") -> 0.16615385 | F54: =IFERROR(F53/F6,"-") -> 0.3104857 | G54: =IFERROR(G53/G6,"-") -> 0.33146085 | H54: =IFERROR(H53/H6,"-") -> 0.38384653 | I54: =IFERROR(I53/I6,"-") -> 0.42464707 | J54: =IFERROR(J53/J6,"-") -> 0.45876572 | K54: =IFERROR(K53/K6,"-") -> 0.48780791
A58: 46112 | B58: Current Capitalization
B59: Current Share Price | F59: =Summary!D12 -> 131.84
B60: Diluted Shares Outstanding (M) | F60: 202.108
B61: Market Cap | F61: =F59*F60 -> 26645.919
B62: (+) Total Debt | F62: 23
B63: (-) Cash & Equivalents | F63: -954
B64: TEV | F64: =SUM(F61:F63) -> 25714.919
B65: 2026E EV / EBITDA | F65: =F64/G40 -> 20.788132
B66: 2027E EV / EBITDA | F66: =F64/H40 -> 13.810375
A68: 48213 | B68: Exit Upside
B69: FY2030E EBITDA | F69: =K40 -> 4407
B70: Exit EV / EBITDA Multiple | F70: =Summary!H12 -> 18
B71: Implied TEV | F71: =F69*F70 -> 79326
A72: 0.15 | B72: (-) Current Net Debt | F72: =-(F62+F63) -> 931
B73: (+) Cumulative Levered FCF | F73: =F79 -> 11448.7
B74: Implied Market Cap | F74: =SUM(F71:F73) -> 91705.7
B75: Current Shares Outstanding | F75: =F60 -> 202.108
B76: Implied Share Price | F76: =F74/F75 -> 453.74602
B78: Remaining Upside
B79: Cumulative Levered FCF | F79: =SUM(G53:K53) -> 11448.7
B80: Gross Upside | F80: =F76/F59-1 -> 2.4416415
B81: MOIC | F81: =F76/F59 -> 3.4416415
A82: =(A68-A58)/365 -> 5.7561644 | B82: IRR | F82: =F81^(1/A82)-1 -> 0.23951154
B85: Illustrative EV / FY2030E EBITDA Sensitivity
B86: Exit Multiple | D86: 10 | E86: 12 | F86: 14 | G86: 16 | H86: 18 | I86: 20 | J86: 22 | K86: 24
B87: Implied TEV | D87: =D86*$F$69 -> 44070 | E87: =E86*$F$69 -> 52884 | F87: =F86*$F$69 -> 61698 | G87: =G86*$F$69 -> 70512 | H87: =H86*$F$69 -> 79326 | I87: =I86*$F$69 -> 88140 | J87: =J86*$F$69 -> 96954 | K87: =K86*$F$69 -> 105768
B88: Plus: Net Cash | D88: =$F$72 -> 931 | E88: =$F$72 -> 931 | F88: =$F$72 -> 931 | G88: =$F$72 -> 931 | H88: =$F$72 -> 931 | I88: =$F$72 -> 931 | J88: =$F$72 -> 931 | K88: =$F$72 -> 931
B89: Plus: Cumulative FCF | D89: =$F$79 -> 11448.7 | E89: =$F$79 -> 11448.7 | F89: =$F$79 -> 11448.7 | G89: =$F$79 -> 11448.7 | H89: =$F$79 -> 11448.7 | I89: =$F$79 -> 11448.7 | J89: =$F$79 -> 11448.7 | K89: =$F$79 -> 11448.7
B90: Implied Market Cap | D90: =SUM(D87:D89) -> 56449.7 | E90: =SUM(E87:E89) -> 65263.7 | F90: =SUM(F87:F89) -> 74077.7 | G90: =SUM(G87:G89) -> 82891.7 | H90: =SUM(H87:H89) -> 91705.7 | I90: =SUM(I87:I89) -> 100519.7 | J90: =SUM(J87:J89) -> 109333.7 | K90: =SUM(K87:K89) -> 118147.7
B91: Implied Share Price | D91: =D90/$F$60 -> 279.30463 | E91: =E90/$F$60 -> 322.91498 | F91: =F90/$F$60 -> 366.52532 | G91: =G90/$F$60 -> 410.13567 | H91: =H90/$F$60 -> 453.74602 | I91: =I90/$F$60 -> 497.35636 | J91: =J90/$F$60 -> 540.96671 | K91: =K90/$F$60 -> 584.57706
B92: Upside / (Downside) | D92: =D91/$F$59-1 -> 1.1185121 | E92: =E91/$F$59-1 -> 1.4492944 | F92: =F91/$F$59-1 -> 1.7800768 | G92: =G91/$F$59-1 -> 2.1108591 | H92: =H91/$F$59-1 -> 2.4416415 | I92: =I91/$F$59-1 -> 2.7724239 | J92: =J91/$F$59-1 -> 3.1032062 | K92: =K91/$F$59-1 -> 3.4339886
B93: Implied IRR | D93: =IFERROR((D91/$F$59)^(1/$A$82)-1,"-") -> 0.13930581 | E93: =IFERROR((E91/$F$59)^(1/$A$82)-1,"-") -> 0.16838735 | F93: =IFERROR((F91/$F$59)^(1/$A$82)-1,"-") -> 0.19438561 | G93: =IFERROR((G91/$F$59)^(1/$A$82)-1,"-") -> 0.21794177 | H93: =IFERROR((H91/$F$59)^(1/$A$82)-1,"-") -> 0.23951154 | I93: =IFERROR((I91/$F$59)^(1/$A$82)-1,"-") -> 0.25943115 | J93: =IFERROR((J91/$F$59)^(1/$A$82)-1,"-") -> 0.27795616 | K93: =IFERROR((K91/$F$59)^(1/$A$82)-1,"-") -> 0.29528564
B96: Memo: Cash Flow Bridge
B97: Cumulative Revenue (FY26E-30E) | F97: =SUM(G6:K6) -> 26397
B98: Cumulative EBITDA | F98: =SUM(G40:K40) -> 13562
B99: Cumulative D&A | F99: =SUM(G44:K44) -> 117
B100: (-) Interest Expense | F100: 0
B101: (-) Taxes | F101: =-(F98-F99)*A72 -> -2016.75
B102: (-) Cumulative Capex | F102: =-SUM(G47:K47) -> -79
B103: Cumulative Levered FCF | F103: =F98+F100+F101+F102 -> 11466.25
